Workbook

Sheet 50-state matrix
A1: State | B1: Letter grade: did the restrictions keep property taxes down? (points, deductions, reasons) | C1: Four-regime scorecard (spending · levy · assessment · rate) | D1: Local spending limit (budgets, appropriations or general revenue) | E1: Local property tax levy limit (cap on property tax revenue growth) | F1: Property tax assessment caps (with all exclusions) | G1: Property tax rate limits (specific rates) | H1: School districts covered by the limits? (education exclusions) | I1: A statewide property tax (additional tax or local pass-through?) | J1: Homestead Exemption (property tax) | K1: Property tax credits, circuit breakers & rebates (separate from homestead exemptions) | L1: State subsidies to local governments to reduce property taxes (mechanism) | M1: Truth-in-taxation laws | N1: Property tax rollback protections | O1: Supermajority requirement for local tax increases (thresholds) | P1: November-ballot requirement for local spending/tax increases | Q1: Statewide restrictions on how localities may spend property tax dollars | R1: Jurisdictions with property taxing authority | S1: Has it worked? Short verdict, then loopholes, workarounds and the full record (incl. shifts to sales/income taxes or fees) | T1: Conservative & free-market analyses (State Policy Network groups, taxpayer groups): links with synopses | U1: Recent reform efforts (2020–2026) & outcomes | V1: Tax Foundation 2026 ranking: effective property tax rate on owner-occupied homes (1 = lowest), with the 2010 rate by the same measure | W1: Notes | X1: Source URLs
A2: Alabama | B2: D. Restriction points 4.5 of 18 (assessment cap 1; rate cap 2; school districts covered 1; use restrictions 0.5). Deductions: built-in loopholes -1; workarounds in practice -0.5; state buydowns +0; data record +0. Total 3 = D (A 11+, B 8.5-10.9, C 5.5-8.4, D 3-5.4, F under 3). Why: Built-in loopholes -1: the 7% assessment cap sunsets after 2027 and excludes new construction, ownership changes and TIF-district property; Mountain Brook, Vestavia Hills and Huntsville are exempt from the Lid Bill ceiling. Workarounds -0.5: local governments lean on sales taxes, fees and occupational taxes (fees 52.5% of local own-source revenue), though voters still reject millage increases (Tuscaloosa, 2024). Buydowns 0: no state program buys down local rates. Record 0: the lowest burden in the country (1.49% of personal income; 0.38% effective rate) offsets some of the fastest recent growth (real per-person collections up 12.9% FY2019-FY2024; U.S. -1.1%). | C2: =((LEFT(D2,3)="Yes")+(LEFT(E2,3)="Yes")+(LEFT(F2,3)="Yes")+(LEFT(G2,3)="Yes"))&" of 4 in force"&IF(((LEFT(D2,7)="Partial")+(LEFT(E2,7)="Partial")+(LEFT(F2,7)="Partial")+(LEFT(G2,7)="Partial"))>0," + "&((LEFT(D2,7)="Partial")+(LEFT(E2,7)="Partial")+(LEFT(F2,7)="Partial")+(LEFT(G2,7)="Partial"))&" partial","")&CHAR(10)&CHAR(10)&IF(LEFT(D2,3)="Yes","✓",IF(LEFT(D2,7)="Partial","◐","✗"))&" Spending limit"&CHAR(10)&IF(LEFT(E2,3)="Yes","✓",IF(LEFT(E2,7)="Partial","◐","✗"))&" Levy limit"&CHAR(10)&IF(LEFT(F2,3)="Yes","✓",IF(LEFT(F2,7)="Partial","◐","✗"))&" Assessment cap"&CHAR(10)&IF(LEFT(G2,3)="Yes","✓",IF(LEFT(G2,7)="Partial","◐","✗"))&" Rate cap" | D2: No. Alabama puts no growth cap on county, municipal or school budgets; local units must simply adopt balanced budgets. The state budget rules cited in earlier versions of this matrix (limits tied to projected revenue) govern state appropriations only. | E2: No. No cap on growth in total property tax revenue. Two features restrain it indirectly: no millage can rise above constitutional limits without a public hearing, an act of the Legislature and a local referendum, and the temporary 7% assessment cap (tax years 2025-2027) slows valuation growth on most parcels. New construction, newly discovered property and growth inside TIF districts still add revenue with no vote. | F2: Partial. Statewide but temporary. Act 2024-344 caps the annual increase in assessed value of Class II real property (commercial, rental and other property not otherwise classed) and Class III real property (owner-occupied homes, farms, forest land, historic property) at 7% a year, starting with the 2025 tax year. Market and current-use values are still determined each year; the cap applies to assessed value only. Class I utility property is not covered. Exclusions (value may rise more than 7%): never-assessed property; additions or improvements (ordinary maintenance does not count); a change in classification; a change in ownership, except transfers between spouses or family members for no or nominal consideration (including at death) and redemptions after foreclosure or tax sale; property inside a tax increment financing district. Sunset: the cap runs through the fiscal year beginning Oct. 1, 2027 unless extended. Authority: Code of Ala. §40-7-2.2 (Act 2024-344, HB 73, signed May 2024). | G2: Yes. Two layers. 1) Overall cap ("Lid Bill"): total ad valorem tax from all levies on a property may not exceed 1% of fair market value for Class III (owner-occupied homes, farm and timber land), 1.25% for Class IV (personal vehicles), 1.5% for Class II and 2% for Class I utility property. Mountain Brook, Vestavia Hills and Huntsville are exempt from this ceiling. 2) Millage caps by levy: state 6.5 mills; county general 5 mills; municipal 5 mills; every school district must levy at least 10 mills (a floor). Assessment ratios are fixed at 10% (Class III), 15% (IV), 20% (II) and 30% (I). Any millage above constitutional limits requires a proposal by the governing body after a public hearing, an act of the Legislature, and majority approval of local voters at a special election. Combined millage in most places sits well below the 100-mill equivalent of the 1% Class III ceiling, so the act-plus-referendum requirement is the working check. Authority: Ala. Const. §217 (Amendment 373, "Lid Bill," ratified Nov. 1978); §§214-216; §269.08 (Amendment 778, 2006, 10-mill school minimum). | H2: Yes. School millage is bound by the same constitutional caps, the act-plus-referendum rule and the 7% assessment cap. The Constitution also sets a 10-mill minimum school levy in every district, and the state Foundation Program counts 10 mills as the required local share, so school taxes have a floor as well as a ceiling. | I2: Yes. An additional state tax that does not replace local levies: 6.5 mills on all taxable property, collected by county officials and remitted to the state. 3 mills go to education (§260), 2.5 mills to the State General Fund, and 1 mill to old-age assistance (DHR share capped at $20.77 million) with the remainder to the Alabama Veterans' Assistance Fund. Homeowners 65+, and disabled or blind homeowners, are exempt from the state levy on their homestead. FY2022 state property tax revenue: about $496 million (Census). | J2: Yes. Regular homestead: $4,000 of assessed value exempt from state taxes and $2,000 of assessed value exempt from county taxes (about $40,000 and $20,000 of market value at the 10% ratio). Counties, cities and other taxing units may raise their exemption to $4,000 of assessed value. Age 65+: exempt from all state taxes; with state AGI under $12,000, $5,000 of assessed value exempt from county taxes; with combined federal taxable income of $12,000 or less, exempt from all ad valorem taxes. Permanently and totally disabled: exempt from all ad valorem taxes, no income test. Blind: exempt from state taxes plus $5,000 assessed value from county taxes. Maximum 160 acres. Many counties add their own senior exemptions through local constitutional amendments (e.g., Limestone County, HB 310 of 2026). Authority: Code of Ala. §§40-9-19 to 40-9-21. | K2: No. No circuit breaker, renter credit or state-funded property tax rebate. Relief comes through exemptions and the low 10% residential assessment ratio. | L2: No. No state program reimburses local governments for property tax revenue lost to state law or pays them to lower rates. The 2025 increase in the business personal property exemption to $100,000 (HB 543) applies to the state levy; counties and cities may adopt a matching local exemption with no state reimbursement. The Foundation Program, which counts 10 mills of local tax toward each district's share, is general school aid and does not count. Authority: Ala. Code § 40-9-1; HB 543 (2025 Reg. Sess.); Ala. Admin. Code r. 810-4-1-.14; Ala. Code § 16-13-231. | M2: No. | N2: No. No rollback, revenue-neutral or certified rate after reappraisal. Rising values raise revenue automatically, limited only by the temporary 7% assessment cap. | O2: No. Millage above constitutional limits needs a simple majority of local voters (after a public hearing and a legislative act). No supermajority of voters or of a governing body is required. | P2: No. Millage referenda are held at special elections; there is no requirement to hold them at November general elections. | Q2: Yes. Alabama millage is purpose-specific by design. Each levy exists under a constitutional section or local amendment that names its purpose: county general (5 mills), county road and bridge, county and district school taxes (with the 10-mill school minimum), and special levies for fire, library, hospital, health and similar services authorized county by county. Dedicated levies may fund only their stated purpose. The state's 6.5 mills are also earmarked (education, General Fund, old-age assistance/veterans). | R2: State (6.5 mills); 67 counties; 462 municipalities; county and city school systems (138 independent school districts in the Census count), whose taxes are levied countywide or by school tax district; special districts created by local act or constitutional amendment (fire protection, hospital, library and similar). Census of Governments 2022: 1,208 local governments, including 541 special districts; most of those special districts are housing, water and soil-conservation authorities that levy no property tax. | S2: Verdict: Failed. Property tax per person rose 48.0% after inflation from FY2002 to FY2024, against 25.9% for the U.S., and grew 12.9% from FY2019 to FY2024 while the U.S. figure fell 1.1%. Why it leaks: The 1978 Lid Bill (Amendment 373) caps millage, yet Alabama has no levy limit or rollback, so local governments collect more each year at the same millage with no vote. No law caps local budgets. Alabama also lacks truth in taxation, which offers transparency and accountability, so these increases reach bills with no notice or hearing. The 7% assessment cap in Act 2024-344 runs only through 2027 unless extended and excludes improvements and property inside TIF districts. How localities get around it: Local constitutional amendments add millage one county at a time. Huntsville is one of three cities exempt from the Lid Bill ceiling. Full record: Has it worked? On the size of the tax, yes. On growth, no. The record (Census, BEA, ACS): state and local property tax was $849 per person in FY2024 (U.S. $2,132), 1.49% of personal income (49th-highest of 50; U.S. 2.89%). After inflation, collections per person (all state and local property tax divided by residents) rose 48.0% from FY2002 to FY2024 (U.S. +25.9%) and rose 12.9% from FY2019 to FY2024 (U.S. -1.1%). The median homeowner paid $890 in 2024 (U.S. $3,211); the median bill rose 20.8% after inflation from 2010 to 2024 (U.S. +9.3%). The Tax Foundation's 2026 ranking puts its effective property tax rate on owner-occupied homes at 0.37%, 2nd-lowest of 50. By the same measure it was 0.37% in 2010 (U.S. 1.00% in 2010, 0.94% in 2024). Why: the 1978 Lid Bill froze low assessment ratios, capped total bills and requires a legislative act plus a referendum for every millage increase, which keeps the level low; with no levy limit and no rollback, rising values flow straight into revenue. The temporary 7% assessment cap began with the 2025 tax year. Revenue shift: local governments moved to other taxes. Property tax supplies only 40% of local tax revenue in Alabama versus 70% nationally, and sales taxes supply 48% (Census, FY2022). Fees and charges are 52.5% of local own-source revenue (34% nationally). The average combined sales tax rate is 9.46%, 5th-highest in the U.S., with local rates up to 11%, and groceries remain taxable. Birmingham and other localities also levy occupational license taxes on wages. Workarounds: local constitutional amendments add millage or exemptions one county at a time; three cities are exempt from the Lid Bill ceiling; TIF-district property is excluded from the 7% cap; current-use valuation keeps timber and farmland taxes very low. Special elections: millage referenda go to special elections with low turnout. In Tuscaloosa the school board, city council and Legislature all approved an 11.5-mill increase (22%, about $17.25 million a year for city schools), and voters still rejected it on Sept. 24, 2024, 5,704 to 4,999, with 16.5% turnout (Alabama Political Reporter). The vote requirement binds even where every elected body backs an increase. Big cities: Tuscaloosa's city rate was already 51.5 mills before that vote, against a 42-mill statewide average (Alabama Political Reporter); larger cities such as Birmingham add occupational taxes on wages (see Revenue shift). Pushback: the Association of County Commissions wants the 7% cap to expire in 2027, citing lost revenue (Randolph County: $1.8 million over two years). The Alabama Policy Institute wants it made permanent (2026 report). | T2: - 1819 News (launched by the Alabama Policy Institute), "Alabama's 7% property tax reappraisal cap expires in 2027 — Will lawmakers extend it?" (Aug. 22, 2026). Reports Sen. David Sessions's plan to extend the cap in 2027, lists every exclusion in the law and gives the county commissions' case for letting it lapse. https://1819news.com/news/item/alabamas-7-property-tax-reappraisal-cap-expires-in-2027-will-lawmakers-extend-it - Alabama Policy Institute, "Alabama Policy Institute Launches Landmark Alabama Tax Relief Report: A Multi-Phase Roadmap for Economic Growth and Fiscal Discipline" (July 15, 2026). A phased tax-cut plan for the 2027 session paid for by spending restraint. On property tax it calls for making the assessment protections permanent by removing the 2027 sunset, and it warns that cutting income taxes without a population-plus-inflation spending cap would push the burden onto sales and property taxes. https://alabamapolicy.org/2026/07/15/alabama-policy-institute-launches-landmark-alabama-tax-relief-report-a-multi-phase-roadmap-for-economic-growth-and-fiscal-discipline/ - Tax Foundation, "Alabama's 2025 Legislative Session Advances Pro-Growth Tax Reforms" (July 9, 2025). Act 2025-344 raises the business tangible personal property tax exemption from $40,000 to $100,000 in market value, effective October 1, 2025, and ends filing for businesses under the threshold; local jurisdictions may opt in. Similar thresholds elsewhere cost "often less than 1 percent of property tax collections." https://taxfoundation.org/blog/alabama-tax-reform-relief-2025/ - 1819 News (launched by the Alabama Policy Institute), "Ainsworth on new property tax cap: ‘We don’t want anybody to get gouged’" (Aug. 14, 2024). Lt. Gov. Will Ainsworth says calls from owners facing reappraisal increases of 20%, 30% and 40% led to the 7% cap in HB 73 (Rep. Phillip Pettus and Sen. David Sessions), effective October 1, 2024. https://1819news.com/news/item/ainsworth-on-new-property-tax-cap-we-dont-want-anybody-to-get-gouged - Alabama Policy Institute, "API: Top 10 Things the AL Legislature Should Accomplish in 2024" (Feb. 5, 2024). Item 8, "Cap Property Tax," notes that county and municipal rates vary widely, so rising valuations hit some owners far harder than others, and urges an assessment cap "to make property tax increases more predictable and lessen the tax burden of Alabama's homeowners." The Legislature enacted the 7% cap (Act 2024-344) that spring. https://alabamapolicy.org/2024/02/05/api-top-10-things-the-al-legislature-should-accomplish-in-2024/ - Free the People (State Policy Network associate): no Alabama property tax work since 2021 was found. - National School Choice Awareness Foundation (State Policy Network associate): no property tax work since 2021 was found. - Americans for Prosperity-Alabama: no property tax item since 2021 was found. Linked list: 5 items on the Analyses sheet (filter State = Alabama); every source URL is linked on the Sources sheet. | U2: 2024: HB 73 (Act 2024-344) passed after large reappraisal increases, creating the 7% annual assessment cap for tax years 2025-2027 (Senate sponsor David Sessions sought 5%). 2026 session: no statewide property tax change. HB 167 (Rep. Kiel) would have replaced the 7% cap with the CPI-U increase; it was referred to House Ways and Means General Fund on Jan. 13, 2026, had not moved by the Alabama State Bar's March 20 tracker and was not enacted. Counties kept adding senior exemptions by local amendment (e.g., Limestone County, HB 310; Colbert and Franklin counties, Acts 2026-28 and 2026-29). 2027 session: extension or tightening of the cap expected to be debated; county commissions oppose extension. Nov. 3, 2026 ballot: four statewide amendments (Lieutenant Governor vacancy and legislative pay, SB 271; merging county school systems, HB 380; school Pledge of Allegiance and student prayer, HB 511; weekly national anthem in schools, SB 5). None concerns property tax (Fox10, Sept. 14, 2026). | V2: 2nd (0.37% effective rate; 0.37% in 2010) | W2: Alabama relies on rate caps: overall 1%/1.25%/1.5%/2% lids, fixed low assessment ratios and a legislative-act-plus-referendum requirement for any millage increase, plus a 7% assessment cap through 2027. It has no spending cap, levy cap or truth-in-taxation law. Property taxes are among the nation's lowest; local governments make up the difference with sales taxes, occupational taxes and fees. | X2: https://www.revenue.alabama.gov/wp-content/uploads/2025/03/HB73.pdf https://www.revenue.alabama.gov/property-tax/homestead-exemptions/ https://law.justia.com/constitution/alabama/CA-888542.html https://www.lincolninst.edu/app/uploads/legacy-files/gwipp/upload/sources/Alabama/2021/al_ad_valorem_tax_guide.pdf https://1819news.com/news/item/alabamas-7-property-tax-reappraisal-cap-expires-in-2027-will-lawmakers-extend-it https://legiscan.com/AL/text/HB310/2026 https://apps.lincolninst.edu/uploads/summary-tables/rate-limits-summary-tables/rate-limits-2022-4.xlsx https://www2.census.gov/programs-surveys/gov-finances/tables/2022/22slsstab1.xlsx https://taxfoundation.org/data/all/state/sales-tax-rates/ https://www.revenue.alabama.gov/property-tax/7-cap-information-hb73-act-2024-344/ https://alison.legislature.state.al.us/files/pdf/SearchableInstruments/2026RS/HB167-int.pdf https://www.alabar.org/assets/2026/03/Tax-3.20.26.pdf https://www.fox10tv.com/2026/09/14/decision-2026-alabama-sample-ballots-now-available-nov-3-election/ https://www.alreporter.com/2024/09/25/tuscaloosa-residents-reject-property-tax-increase-for-schools/ https://alabamapolicy.org/2024/02/05/api-top-10-things-the-al-legislature-should-accomplish-in-2024/ https://www.tuscco.com/wp-content/uploads/2026/05/Insert-for-2026-Valuation-Notices-CAP-Doc-3-1.pdf
A3: Alaska | B3: C. Restriction points 6.75 of 18 (spending limit 2; levy limit 2; rate cap 2; school districts covered 0.5; use restrictions 0.25). Deductions: built-in loopholes -1; workarounds in practice -0.5; state buydowns +0; data record +0.5. Total 5.75 = C (A 11+, B 8.5-10.9, C 5.5-8.4, D 3-5.4, F under 3). Why: Built-in loopholes -1: debt taxes sit outside every state limit, the 30-mill cap sits far above most local rates, and the per-capita levy ceiling binds mainly on the North Slope Borough. Workarounds -0.5: the Anchorage Assembly loosened its tax cap in 2015 (voters reversed it in 2016) and drafted a sales tax partly outside the cap; Mat-Su swapped its revenue cap for a 10.5-mill rate cap in 2018. Buydowns 0. Record +0.5: real per-person collections fell 9.6% FY2019-FY2024 and real homeowner bills fell 7.3% 2010-2024, though the burden is above average (3.20% of personal income; 1.06% effective rate). | C3: =((LEFT(D3,3)="Yes")+(LEFT(E3,3)="Yes")+(LEFT(F3,3)="Yes")+(LEFT(G3,3)="Yes"))&" of 4 in force"&IF(((LEFT(D3,7)="Partial")+(LEFT(E3,7)="Partial")+(LEFT(F3,7)="Partial")+(LEFT(G3,7)="Partial"))>0," + "&((LEFT(D3,7)="Partial")+(LEFT(E3,7)="Partial")+(LEFT(F3,7)="Partial")+(LEFT(G3,7)="Partial"))&" partial","")&CHAR(10)&CHAR(10)&IF(LEFT(D3,3)="Yes","✓",IF(LEFT(D3,7)="Partial","◐","✗"))&" Spending limit"&CHAR(10)&IF(LEFT(E3,3)="Yes","✓",IF(LEFT(E3,7)="Partial","◐","✗"))&" Levy limit"&CHAR(10)&IF(LEFT(F3,3)="Yes","✓",IF(LEFT(F3,7)="Partial","◐","✗"))&" Assessment cap"&CHAR(10)&IF(LEFT(G3,3)="Yes","✓",IF(LEFT(G3,7)="Partial","◐","✗"))&" Rate cap" | D3: Partial. No statewide spending or revenue cap on municipalities. The binding limits are local and voter-imposed: Anchorage's 1983 charter "tax cap" sets the maximum total taxes the Municipality may collect each year at the prior year's taxes adjusted for the five-year average change in population and inflation, and the Assembly may not adopt a budget that exceeds it. Other municipalities have adopted their own caps, some since loosened (see Loopholes). Authority: Anchorage Municipal Charter §14.03; Anchorage Municipal Code 12.25. | E3: Partial. State law: a per-capita levy ceiling (AS 29.45.090) limits operating property tax revenue to what a capped rate would raise on a hypothetical tax base of 375%, 300% or 225% of the statewide average per-capita full value (sliding by mill rate), with a flat $1,500-per-resident alternative. It only binds municipalities with exceptionally large tax bases per resident, chiefly the North Slope Borough's oil infrastructure. Local voter-approved caps (Anchorage, Matanuska-Susitna Borough, City of Fairbanks and others) do the work elsewhere. Taxes for voter-approved bonds are excluded from all state limits (AS 29.45.100). Authority: AS 29.45.090, 29.45.100 (enacted 1972). | F3: No. No annual assessment growth cap. Property is assessed at full and true value each year. The mandatory senior/disabled-veteran exemption (first $150,000) is the only statewide shield for long-time owners. | G3: Yes. Operating levies of any municipality may not exceed 30 mills (3% of assessed value) in a year; second-class cities are limited to 20 mills (2%). Taxes for bonded debt are outside the limits. Few municipalities approach 30 mills; most levy well below it. Authority: AS 29.45.090; AS 29.45.590 (second-class cities); AS 29.45.100 (debt excluded). | H3: Partial. Alaska has no independent school districts; boroughs and home-rule/first-class cities fund their schools inside the same 30-mill operating limit. The state foundation formula (AS 14.17.410) requires a minimum local contribution (the equivalent of 2.65 mills on full value) and caps how much more a municipality may contribute, so school-related local taxes have both a floor and a ceiling set by the state. | I3: Partial. The only state property tax is a 20-mill (2%) tax on oil and gas exploration, production and pipeline transportation property. Municipal taxes on the same property are credited against it, so in organized areas it mostly serves as a state backstop; in the unorganized borough the state keeps the full tax. It applies to one industry and does not replace local levies. FY2022 state property tax revenue: about $125 million (Census). Authority: AS 43.56. | J3: Yes. Mandatory: the first $150,000 of assessed value of a permanent home owned and occupied by a resident 65 or older, a veteran with a 50%+ service-connected disability, or certain surviving spouses is exempt from municipal property tax (municipalities may grant more). Local option: municipalities may exempt up to $75,000 of assessed value of any owner-occupied residence (a general "homestead" exemption); whether and how much varies by municipality. There is no statewide general homestead exemption for all owners. Authority: AS 29.45.030(e); AS 29.45.050. | K3: No. No statewide circuit breaker, renter credit or property tax rebate. Some municipalities run local senior hardship programs. The Permanent Fund Dividend is a cash payment unrelated to property tax. | L3: No. State law requires the state to reimburse boroughs and cities for real property tax lost to the mandatory exemption of the first $150,000 of assessed value on homes of residents 65 and older and disabled veterans, prorated when appropriations fall short. The Legislature has not funded the reimbursement since 1997, so no state money reaches municipalities for it; they absorb the cost, which the Alaska Municipal League put at over $105 million a year in 2023. K-12 foundation aid, with its required local contribution, and Community Assistance revenue sharing are general aid and do not count. Authority: AS 29.45.030(e); AS 29.45.030(g); AS 14.17.410; AS 29.60.850. | M3: No. | N3: No. No state rollback rule. In Anchorage the charter tax cap has a similar effect: when assessments rise faster than the cap allows, the mill rate must fall. | O3: No. State law requires no supermajority to raise property taxes. Bonds require majority voter approval. Exceeding local charter caps follows each charter's terms (typically a public vote). | P3: No. Municipal elections are generally held in October (April in Anchorage); bond and tax questions go on those ballots or special elections. | Q3: Partial. Operating levies are general purpose. Borough and city "service area" levies (roads, fire, street lights and similar) may fund only the service in that area, and debt levies are dedicated to the bonds voters approved. | R3: Only municipalities levy property tax: organized boroughs, unified home-rule municipalities and cities. Per Alaska Taxable 2025, 15 of 19 organized boroughs/unified municipalities and 21 of 145 cities levy one. School systems are departments of boroughs and cities (55 dependent school systems in the Census count), and borough service areas levy within the borough's taxing power. The unorganized borough has no local property tax; the state's 20-mill oil and gas property tax applies statewide. Census of Governments 2022: 181 local governments (15 county-type boroughs, 149 municipalities, 17 special districts, none of which levy property tax). | S3: Verdict: Partly. Property tax per person rose 9.0% after inflation from FY2002 to FY2024, against 25.9% for the U.S., and fell 9.6% from FY2019 to FY2024. Why it leaks: The 30-mill operating cap (AS 29.45.090) is a rate cap few municipalities approach, and the per-capita levy ceiling binds chiefly the North Slope Borough. Taxes for voter-approved bonds fall outside all state limits. Alaska has no assessment cap. Restraint comes from local voter caps such as Anchorage's 1983 charter tax cap, and part of the recent decline came from falling oil and gas property tax. How localities get around it: In 2015 the Anchorage Assembly loosened its tax cap formula until voters reversed it with Proposition 8 in 2016. In 2018 the Matanuska-Susitna Borough Assembly replaced its revenue-growth cap with a fixed 10.5-mill rate cap. Full record: Has it worked? Growth has been held down; the level remains high. Statewide limits are loose (a 30-mill cap few municipalities approach and a per-capita ceiling aimed at the North Slope Borough's oil base), so restraint comes from local voter caps, which local officials have tried to loosen. The record (Census, BEA, ACS): state and local property tax was $2,456 per person in FY2024 (U.S. $2,132), 3.20% of personal income (13th-highest of 50; U.S. 2.89%). After inflation, collections per person (all state and local property tax divided by residents) rose 9.0% from FY2002 to FY2024 (U.S. +25.9%) and fell 9.6% from FY2019 to FY2024 (U.S. -1.1%). The median homeowner paid $3,976 in 2024 (U.S. $3,211); the median bill fell 7.3% after inflation from 2010 to 2024 (U.S. +9.3%). The Tax Foundation's 2026 ranking puts its effective property tax rate on owner-occupied homes at 0.94%, 31st-lowest of 50. By the same measure it was 1.00% in 2010 (U.S. 1.00% in 2010, 0.94% in 2024). Why: two forces outside the limits explain part of the decline. The state's oil and gas property tax fell from $215 million to $131 million over the period, and population grew less than 1%. The data cannot separate the effect of local caps such as Anchorage's from those forces. Anchorage: in Oct. 2015 the Assembly loosened the tax cap's growth formula; voters reversed it in April 2016 with Proposition 8 (60%+), which also tied the cap to taxes collected (the looser formula had used the maximum allowable). Anchorage says property taxes have held steady since 1983 under the cap. In 2025 the Assembly drafted a sales tax structured partly "outside the tax cap" before postponing it indefinitely; Mayor LaFrance's 3% sales tax proposal (1% earmarked for property tax relief) was postponed indefinitely in January 2026 in exchange for a one-time $12 million school levy. In April 2026 voters rejected that levy, a $79 million school bond and a police facilities bond while approving seven of ten areawide measures; residents cited rising assessments and an appraisal method change (Anchorage Daily News). Fairbanks: in June 2026 the City of Fairbanks council voted 5-1 to raise its rate from 5.833 to 6.381 mills, partly to pay a 2025 wrongful-conviction settlement, with a further payment due in 2027; the mayor said the usual formula would have produced 7.2 mills (Alaska's News Source, June 13, 2026). The Fairbanks North Star Borough held its FY2027 mill rate flat by drawing about $600,000 from its general fund (Alaska's News Source, May 31, 2026). Matanuska-Susitna Borough: in 2018 the Assembly replaced its revenue-growth cap with a fixed 10.5-mill rate cap, which lets revenue rise with assessed values. Revenue mix: property tax supplies 76% of local taxes (U.S.: 70%); local sales taxes (average 1.82%, up to 7.85%), bed taxes and fees fill the rest. Large resource projects often pay boroughs negotiated payments in lieu of taxes, which take the place of standard levies. | T3: - Alaska Policy Forum, "Testimony: Oppose New Property Taxes" (June 8, 2023; testimony dated April 18, 2023). CEO Bethany Marcum opposed SB 77, which would let boroughs and cities tax "blighted" property, because the bill set no guardrails on what counts as blight and protected only an owner's primary residence; she cited a New Orleans blight-tax effort that collected only 3% of the fines levied. https://alaskapolicyforum.org/2023/06/testimony-tax-blighted-property/ - Alaska Policy Forum and Tax Foundation, Jared Walczak, "Economic Implications of an Alaska Income Tax or Its Alternatives" (Oct. 4, 2022). A full report opposing a state income tax; it finds Alaska would need income tax burdens three times California's to match the average state's reliance on the tax, and it points to New Jersey, where an income tax adopted to cut school reliance on local property taxes "did not translate into lower property tax burdens" (effective rate 2.21% on owner-occupied housing against a 1.08% national average). https://alaskapolicyforum.org/2022/10/economic-implications-of-an-alaska-income-tax-or-its-alternatives/ - Alaska Policy Forum, "Alaska Property Taxes, Ranked" (Aug. 3, 2022). Summarizes the Tax Foundation's ranking (Alaska 24th on property tax burden) and argues that heavy reliance on property tax beats a state income or sales tax: property tax is more transparent, funds local services residents can see, and is already restrained by Alaska's rate and levy limits; urges residents to scrutinize school bonds and levies. https://alaskapolicyforum.org/2022/08/alaska-property-taxes-ranked/ - Americans for Prosperity-Alaska: no Alaska property tax item since 2021 was found. Linked list: 3 items on the Analyses sheet (filter State = Alaska); every source URL is linked on the Sources sheet. | U3: 2026: Governor Dunleavy sought to nearly eliminate state and municipal property taxes on the proposed Alaska LNG pipeline (HB 381 / SB 2001), replacing them with payments tied to gas throughput. The Senate passed a version narrowly in July; the House rejected it; a third special session ended Aug. 25, 2026 without action. 2026 (Anchorage): the mayor's sales tax proposal was tabled in January; in April voters rejected the school bond, the police bond and a one-time levy. 2025: Anchorage Assembly shelved a proposed sales tax (partly for property tax relief) in March. 2016: Anchorage voters tightened the tax cap (Prop 8). 2018: Mat-Su converted its cap to a 10.5-mill rate cap. 2025-2026 (34th Legislature): HB 169 (Rep. Tomaszewski, April 2, 2025) would have raised the mandatory senior and disabled-veteran exemption from $150,000 to $250,000 of assessed value; it never left House Community and Regional Affairs. SB 259 (Sen. Bjorkman, 2026) would have allowed an optional municipal limit on annual increases in the value of owner-occupied homes; it was referred to Senate Finance on April 28, 2026 and was not enacted. In Feb. 2025 Anchorage Assembly Member Sulte drafted a resolution urging the Legislature to authorize a cap modeled on Florida's "Save Our Homes." 2024: late in the session the Senate Finance Committee proposed tripling the senior exemption to $450,000; it did not become law (the 2025 HB 169 text still shows $150,000). Nov. 3, 2026 ballot: Ballot Measure 2 (repeal top-four ranked-choice voting) and Ballot Measure 3 (citizenship requirement for voting); Ballot Measure 1 (campaign contribution limits) was on the Aug. 18 primary ballot. None concerns property tax. | V3: 31st (0.94% effective rate; 1.00% in 2010) | W3: Alaska has a statutory rate cap (30 mills) and a per-capita levy ceiling, but no assessment cap, no truth-in-taxation and no statewide spending limit. Only 36 municipalities levy property tax at all. Restraint, where it exists, comes from voter-adopted municipal caps such as Anchorage's 1983 tax cap, which voters had to defend against Assembly loosening in 2016. | X3: https://www.commerce.alaska.gov/dcra/admin/Taxable/ViewFile/2de31798-e2aa-42c9-8a50-43e1c7c6ddb8 https://www.akleg.gov/basis/statutes.asp#29.45.090 https://www.akleg.gov/basis/statutes.asp#43.56 https://www.muni.org/Departments/Assembly/SiteAssets/Pages/FOCUS-Budget-and-Taxes/2026%20Property%20Taxes%20Fact%20Sheet.pdf https://muni.org/Departments/Assembly/Documents/AIM%208-2025.pdf https://www.adn.com/article/20160405/anchorage-voters-support-tax-cap-initiative-and-marijuana-taxes https://matsugov.us/news/whistle-stop-mat-su-on-the-new-tax-cap https://www.adn.com/politics/alaska-legislature/2026/08/25/3rd-special-session-on-alaska-lng-ending-after-lawmakers-decline-to-take-up-dunleavys-bill/ https://www.alaskasnewssource.com/2025/03/19/anchorage-sales-tax-proposal-go-before-voters-tuesday-night https://www.lincolninst.edu/app/uploads/2025/01/levy_limits_2022.xlsx https://law.justia.com/codes/alaska/title-29/chapter-45/article-1/section-29-45-090/ https://www.adn.com/alaska-news/anchorage/2026/01/14/lafrance-says-anchorage-sales-tax-conversations-will-continue-despite-tabling/ https://www.adn.com/alaska-news/anchorage/2026/05/12/tax-concerns-and-school-district-distrust-shaped-anchorages-mixed-municipal-election-results/ https://www.alaskasnewssource.com/2026/01/10/we-do-math-sales-tax-vs-property-taxes-which-saves-you-more-money/ https://www.akleg.gov/basis/Bill/Detail/34?Root=HB%20169 https://www.akleg.gov/pdf/34/Bills/HB0169A.pdf https://www.akleg.gov/basis/Bill/Detail/34?Root=SB%20259 https://thealaskacurrent.com/2024/05/13/property-tax-cut/ https://muni.org/Departments/Assembly/Documents/DRAFT%20AR%20re%20Property%20Tax%20Excalation%20Limitations.pdf https://www.alaskasnewssource.com/2026/06/13/city-fairbanks-establishes-tax-rate-current-year/ https://www.alaskasnewssource.com/2026/05/31/fairbanks-borough-assembly-passes-fy27-budget-with-no-increase-mill-rate/ https://alaskapolicyforum.org/2023/06/testimony-tax-blighted-property/ https://theballotbrief.com/measures/alaska
A4: Arizona | B4: A. Restriction points 16.25 of 18 (spending limit 4; levy limit 4; assessment cap 2; rate cap 2; truth in taxation 1; rollback 1; supermajority 1; school districts covered 0.5; November-ballot rule 0.5; use restrictions 0.25). Deductions: built-in loopholes -1.5; workarounds in practice -1; state buydowns +0; data record +1. Total 14.75 = A (A 11+, B 8.5-10.9, C 5.5-8.4, D 3-5.4, F under 3). Why: Built-in loopholes -1.5: secondary taxes for bonds, overrides and special districts sit outside the 1% and 2% caps; unused levy capacity carries forward; voters can replace city spending limits through home rule options; the Legislature waives the school expenditure limit every year. Workarounds -1: 23 cities raised primary taxes above truth-in-taxation limits for FY2027 and ten levied to their maximum (ATRA); Phoenix and Gilbert raised sales taxes and fees; the Yuma County Hospital District levied without an election. Buydowns 0: Additional State Aid ($416 million in FY2024) equals 4.3% of state and local property tax, below the 5% threshold. Record +1: real per-person collections fell 2.7% FY2002-FY2022 (U.S. +23.4%) and 9.7% FY2019-FY2024; real homeowner bills fell 11.0% 2010-2024; 1.94% of personal income. | C4: =((LEFT(D4,3)="Yes")+(LEFT(E4,3)="Yes")+(LEFT(F4,3)="Yes")+(LEFT(G4,3)="Yes"))&" of 4 in force"&IF(((LEFT(D4,7)="Partial")+(LEFT(E4,7)="Partial")+(LEFT(F4,7)="Partial")+(LEFT(G4,7)="Partial"))>0," + "&((LEFT(D4,7)="Partial")+(LEFT(E4,7)="Partial")+(LEFT(F4,7)="Partial")+(LEFT(G4,7)="Partial"))&" partial","")&CHAR(10)&CHAR(10)&IF(LEFT(D4,3)="Yes","✓",IF(LEFT(D4,7)="Partial","◐","✗"))&" Spending limit"&CHAR(10)&IF(LEFT(E4,3)="Yes","✓",IF(LEFT(E4,7)="Partial","◐","✗"))&" Levy limit"&CHAR(10)&IF(LEFT(F4,3)="Yes","✓",IF(LEFT(F4,7)="Partial","◐","✗"))&" Assessment cap"&CHAR(10)&IF(LEFT(G4,3)="Yes","✓",IF(LEFT(G4,7)="Partial","◐","✗"))&" Rate cap" | D4: Yes. Constitutional expenditure limit approved by voters June 3, 1980. Each county, city and town may spend "local revenues" only up to its fiscal 1979-80 base, adjusted every year for population growth and inflation (GDP implicit price deflator); the Economic Estimates Commission publishes each limit by April 1. Excluded from "local revenues": bond proceeds and debt service, federal grants, state-shared money counted under the state's own limit, investment earnings, voter-approved capital accumulations, intergovernmental contract payments and several smaller items. Ways around it, all voter-approved: (1) a city or town "home rule option" (alternative expenditure limitation) adopted by majority vote at a regular candidate election, good for four fiscal years, then renewable; (2) a permanent base adjustment (2/3 of the council or an initiative, then majority of voters); (3) a one-time override for a specific amount (2/3 of the governing board plus majority of voters); (4) disaster spending (2/3 of the board if declared by the governor, 70% if not). School districts are under a separate statewide aggregate expenditure limit (AEL): FY1979-80 local spending adjusted for enrollment and inflation, times 1.10. Only a 2/3 vote of each house of the Legislature can lift it, one year at a time. Community college districts have their own limit. Authority: Ariz. Const. art. IX §20 (cities, towns, counties; 1980) and §21 (schools, community colleges; Prop 109, 1980). | E4: Yes. Primary property tax levies of counties, cities, towns and community college districts may grow no more than 2% a year, plus taxes on property new to the rolls (new construction, annexations). The limit is figured from the maximum allowable levy each year even if a government levied less, so unused capacity carries forward; Prop 101 (2006) reset the base to the amount each government levied in 2005, beginning in 2007. Voters may approve levies above the limit. Excluded: debt service and other long-term obligations; levies of special-purpose districts (fire, flood control, library, community facilities districts, etc.); county taxes collected for school districts. School district primary levies are instead fixed by the state-set Qualifying Tax Rate (see Rollback). Fire districts have a separate cap: the lesser of 1.08 times last year's levy or a rate ceiling the Legislature raised from $3.25 to $3.75 per $100 (2022-2024). Authority: Ariz. Const. art. IX §19 (1980; amended by Prop 101, 2006); A.R.S. §42-17051; A.R.S. §48-807 (fire districts). | F4: Yes. Limited Property Value (LPV): the taxable value of each parcel of locally assessed real property may rise no more than 5% a year over the prior year's LPV (and never above full cash value). LPV is used for both primary and secondary taxes since tax year 2015. There is no reset on sale: the limited value stays with the property when it changes hands. Before 2015 the cap was the greater of 10% or one-quarter of the gap to market value, and applied to primary taxes only. Exceptions: new construction, additions and other modifications, changes of use, splits or combinations, and (since Laws 2025, ch. 96) property that loses the senior valuation freeze or a statutory valuation formula are valued at the LPV-to-market ratio of comparable property; the cap does not apply to mines, producing oil/gas/geothermal interests, utilities, pipelines, airline aircraft, standing timber or personal property. Senior valuation freeze: owners 65+ with income under 400% of the SSI rate (500% for two or more owners) may freeze the value of their home after two years of residence. Authority: Ariz. Const. art. IX §18(3)-(7) (Prop 117, approved Nov. 2012; senior freeze, Prop 104, 2000); A.R.S. §42-13301 et seq. | G4: Yes. Primary property taxes on residential property from all taxing jurisdictions combined may not exceed 1% of the home's Limited Property Value ($10 per $100 of net assessed value on Class 3 owner-occupied homes). Outside the 1% cap: taxes for bonds and other long-term debt; levies of special-purpose districts; and any tax approved by voters to exceed a budget, expenditure or tax limit (school and city overrides). These "secondary" taxes average roughly $4 per $100 of assessed value on top of primary rates around $7 (2023 data). Who pays when the cap is breached: the state. When combined primary rates on a home exceed $10 per $100, the state backfills the excess through Additional State Aid, so local units face no requirement to coordinate lower rates (state cost for the 1% backfill is capped at $1 million per county, with the remainder apportioned by the Property Tax Oversight Commission). Authority: Ariz. Const. art. IX §18(1)-(2) (1980); A.R.S. §15-972(E), (K). | H4: Partial. School districts are outside the 2% levy limit and the city/county expenditure limit, but are covered by other limits: the statewide aggregate expenditure limit (AEL), the 1% residential cap on primary taxes, the 5% LPV cap, and a state-set Qualifying Tax Rate for their primary levy that must fall each year to offset value growth unless 2/3 of the Legislature votes otherwise. The AEL has been lifted by 2/3 legislative votes every recent year (FY2022 by $1.15 billion; also FY2025 and FY2026). Voter-approved overrides (up to 15% of the revenue control limit for maintenance and operations) and bonds sit outside the 1% cap. | I4: Partial. No state-levied property tax since Laws 2022, ch. 317 repealed the State Equalization Assistance Property Tax Rate beginning FY2023. The state still sets the Qualifying Tax Rate every school district must levy as its local share of the K-12 formula; the revenue stays with the district and offsets state aid, so it functions as a state-set uniform school levy, collected locally. | J4: Partial. No general homestead exemption. Owner-occupied homes are assessed at 10% of LPV (commercial property 16% in FY2026, falling to 15% by FY2028). The constitutional exemption for widows, widowers and persons with disabilities removes $4,873 of assessed LPV in tax year 2026 if total Arizona property is under $36,454 of assessed value and household income is under $39,865 ($47,826 with minor children). Authority: Ariz. Const. art. IX §2.1-2.2; A.R.S. §42-11111. | K4: Yes. Homeowner's Rebate: the state pays 50% of each owner-occupied home's school district primary tax at the Qualifying Tax Rate (47.19% before 2022), up to $600 per home; it appears as a credit on the bill. 1% cap credit: any primary tax above 1% of LPV is credited on the bill and paid by the state (see Rate limits). Property Tax Refund Credit: small refundable income tax credit for very-low-income owners and renters age 65+ or on SSI. Authority: A.R.S. §15-972; §43-1072. | L4: Yes. Additional State Aid pays school districts for the Homeowner's Rebate, which cuts the school district primary tax on each owner-occupied home by up to 50% of the qualifying tax rate, capped at $600 per parcel. It also pays for credits that hold a home's combined primary property taxes to 1% of full cash value. Both reductions are applied on the tax bill. The General Fund appropriation is $531.6 million in FY2026 and $552.0 million in FY2027, including $4.6 million for the cut in the commercial assessment ratio to 15.5% and $825,000 for the higher business personal property exemption. Authority: Ariz. Const. art. IX, § 18; A.R.S. § 15-972; A.R.S. § 41-1276; JLBC FY2027 Appropriations Report (Department of Education). | M4: Partial. Counties, cities, towns and community college districts: if the proposed primary levy, excluding new construction, exceeds the prior year's levy, the governing body must publish a "Truth in Taxation Hearing - Notice of Tax Increase" twice in a newspaper (or mail it to all registered voters), issue a press release, hold a hearing, and adopt the increase by roll-call vote. An increase of 15% or more requires a unanimous roll call. A body that skips the procedure may not levy more than last year's amount plus new construction. Schools follow a parallel statute; the Legislature itself must hold a TnT hearing and win 2/3 of each house to set school Qualifying Tax Rates above the "truth in taxation rate." Coded Partial because Arizona meets one of the three key truth-in-taxation requirements (a rollback rate calculation, mailed parcel-specific notices and a governing-body vote to exceed the rollback rate). Authority: A.R.S. §42-17107; §15-905.01; §41-1276(E)-(G). | N4: Yes. For school taxes, rollback is automatic: each year the Joint Legislative Budget Committee computes Qualifying Tax Rates that offset the change in net assessed value, and those rates apply unless 2/3 of each house votes for higher ones. For counties, cities and community colleges the 2% levy limit and the TnT hearing/roll-call requirement serve the same purpose. Authority: A.R.S. §41-1276; §42-17051; §42-17107. | O4: Yes. Governing-body supermajorities: 2/3 of a city, town or county board to refer a one-time override or permanent base adjustment (plus majority voter approval); 2/3 for disaster spending declared by the governor; 70% for undeclared disasters; unanimous roll call for a primary levy increase of 15% or more. State level: 2/3 of each house to waive the school AEL or to set school tax rates above the TnT rate. Voter approval of overrides and bonds is by simple majority. Authority: Ariz. Const. art. IX §20(2), (6); §21(3); A.R.S. §42-17107(A)(4); §41-1276(G). | P4: Yes. Any election authorizing secondary property taxes (bonds, budget overrides) by a county, city, town, school district, community college district or special taxing district must be held on the November general election date. Elections to authorize or raise city, town or county transaction privilege (sales) taxes may be held only in November of even-numbered years. Home rule (alternative expenditure limit) votes may be held at the city's regular candidate election, which can fall in spring. Authority: A.R.S. §16-204(F)(4) (and parallel paragraphs). | Q4: Partial. Primary levies are general-purpose. Secondary levies are restricted to their voter-approved purpose: bond debt service, a specific override, or a special district's function (fire, flood control, library, jail, community facilities). School override revenue must be spent within the override's stated purpose and term. | R4: 15 counties; 91 cities and towns; school districts (242 independent districts in the Census count; charter schools do not tax); 10 community college districts; special taxing districts under Title 48, including 145 fire districts, county flood control and library districts, hospital and health districts, irrigation and electrical districts, sanitary districts, street lighting improvement districts and developer-formed community facilities districts (CFDs). Census of Governments 2022: 674 local governments, including 326 special districts. | S4: Verdict: Worked. Property tax per person fell 7.7% after inflation from FY2002 to FY2024 while the U.S. figure rose 25.9%, though Additional State Aid, a $531.6 million state subsidy of homeowners' school taxes in FY2026, counts against Arizona. Why it leaks: Secondary taxes for debt and voter-approved overrides sit outside the 1% residential cap and the 2% primary levy limit (Ariz. Const. art. IX, §§18-19). The Legislature has waived the school aggregate expenditure limit year after year. Because the state backfills rates above 1%, local units face no requirement to coordinate lower rates. How localities get around it: The Yuma County Hospital District had the Board of Supervisors levy its tax for three years with no election. Cities replace the 1980 expenditure limit through home rule votes or permanent base adjustments, such as Marana's Prop 495. Full record: Has it worked? Yes, by every measure used here, though every layer has a release valve and part of the 1% cap's cost lands on state taxpayers. The record (Census, BEA, ACS): state and local property tax was $1,269 per person in FY2024 (U.S. $2,132), 1.94% of personal income (42nd-highest of 50; U.S. 2.89%). After inflation, collections per person (all state and local property tax divided by residents) fell 7.7% from FY2002 to FY2024 (U.S. +25.9%) and fell 9.7% from FY2019 to FY2024 (U.S. -1.1%). The median homeowner paid $1,828 in 2024 (U.S. $3,211); the median bill fell 11.0% after inflation from 2010 to 2024 (U.S. +9.3%). The Tax Foundation's 2026 ranking puts its effective property tax rate on owner-occupied homes at 0.48%, 4th-lowest of 50. By the same measure it was 0.57% in 2010 (U.S. 1.00% in 2010, 0.94% in 2024). The 5% cap on limited property value (Prop 117, in force since 2015) and the 2% primary levy limit keep most of the growth in values off homeowners' bills. Expenditure limit: the 1980 formula binds, so cities routinely ask voters to replace it; home rule options (4-year alternative limits) and permanent base adjustments are common (e.g., Sedona, San Luis home rule; Marana permanent base adjustment, Prop 495). The school AEL has been exceeded and waived by the Legislature year after year (by $1.15 billion for FY2022). Secondary taxes: bonds, voter overrides and special districts sit outside the 1% cap and the 2% levy limit. Some districts skip the vote entirely: the Yuma County Hospital District had the Board of Supervisors levy its tax for three years with no election; after a Goldwater Institute suit the district deposited more than $4 million with the county treasurer in 2025 to credit back on 2025-26 bills, and the tax ended. Developer-formed community facilities districts put additional property taxes on new subdivisions; fire districts gained higher rate ceilings in 2022-2024. Truth in taxation: for FY2027, 23 cities and towns raised primary property taxes above their truth-in-taxation limits (largest: Kearny 24.3%, Huachuca City 9.1%, Clarkdale 8.4%, Flagstaff 6.9%, Prescott 6.1%, Surprise 6%) and ten levied to their constitutional maximum. Only Peoria and Phoenix included the required notice in their budgets. City primary levies total $499.4 million (up 4.5%), plus $491 million in secondary taxes for voter-approved bonds (Arizona Tax Research Association, Sept./Oct. 2026). Reserves: city general fund cash reached $4.6 billion in FY2027, 46.6% of general fund budgets and up 64% since FY2022; 19 cities hold reserves above 100% of a year's spending, led by Paradise Valley (387.6%) and Queen Creek (367.2%) (ATRA). Cities raising taxes sit on cash well above the 15% the Government Finance Officers Association recommends. Big cities: Phoenix raised its sales tax by half a point to 2.8% in July 2025 and its primary levy by 1.22%; Gilbert raised its sales tax from 1.5% to 2% and added a 2% use tax in Jan. 2025, and its water bills rose 50% in 2024 and another 25% in April 2025 (Arizona Free Enterprise Club, Dec. 4, 2025). State backfill: local units are never required to keep combined primary rates under 1%; the state backfills the overage through Additional State Aid (its cost for the 1% backfill is capped at $1 million per county, with the rest apportioned by the Property Tax Oversight Commission) plus a 50% school-tax rebate, about $532 million in FY2026, a subsidy that shields local governments from the consequences of their own rates. Revenue shift: Arizona cities fund operations mainly with transaction privilege (sales) taxes, including taxes on groceries in many cities. Sales taxes supply 38% of local tax revenue (U.S.: 18.5%) and property tax 57.6% (U.S.: 70%) (Census, FY2022); the combined sales tax rate averages 8.52%. Mesa, the third-largest city, levies no primary property tax at all. | T4: - Arizona Tax Research Association, "City Budgets Maintain Strong Reserves—TNT Noncompliance Remains a Problem" (Sept.-Oct. 2026 newsletter). City and town property taxes reach $991 million in FY2027, up 22.8% in five years and 56.8% in ten; of the 23 cities and towns subject to truth-in-taxation requirements, only Peoria and Phoenix included the required notices in their budgets, while city cash reserves reached $4.6 billion (46.6% of general fund budgets). https://www.arizonatax.org/sites/default/files/publications/newsletters/file/ATRA%20Sept%20Oct%202026%20Newsletter.pdf - Arizona Free Enterprise Club, "Addressing Affordability in the 2026 Legislative Session" (Jan. 7, 2026). Says cities and towns have been raising sales and use taxes, fees and rates even as the Legislature cut taxes, and urges a moratorium on local tax, rate and fee hikes, voter approval for any local tax increase, "absolute caps on local tax rates," and an end to property tax hikes that support empty and underused schools. https://azfree.org/blog/2026/01/07/addressing-affordability-in-the-2026-legislative-session/ - Arizona Free Enterprise Club, "The Arizona Free Enterprise Club recommends that Maricopa County voters vote NO on Proposition 409" (Oct. 28, 2025). Opposed Valleywise Health's $898 million bond, which would stack 30 more years of debt on Maricopa County homeowners on top of the $935 million bond voters approved in 2014, and objected to placing it on an off-cycle, low-turnout ballot. Voters approved it in November 2025. https://azfree.org/blog/2025/10/28/the-arizona-free-enterprise-club-recommends-that-maricopa-county-voters-vote-no-on-proposition-409/ - Goldwater Institute, "Yuma County Refunding Illegal Property Tax after Goldwater Legal Challenge" (Aug. 22, 2025). The Yuma County Hospital District had the county levy its tax for three years without the election state law requires; after Goldwater sued in 2023, the district put up more than $4 million, every dollar collected, as credits on 2025-26 bills, and the tax ended. https://www.goldwaterinstitute.org/yuma-county-hospital-district-treasurer-refunding-illegal-property-tax-after-goldwater-legal-challenge/ - Common Sense Institute Arizona, Glenn Farley, "Arizona Prop. 312 The Fiscal & Economic Consequences of Unmitigated Public Nuisances" (Sept. 25, 2024). Analysis of the Goldwater-drafted measure letting owners claim property tax refunds for documented costs when a city or county fails to enforce laws on illegal camping and similar nuisances; it finds estimated market rents for commercial property in the affected parts of Phoenix rose only 15.7% from 2019 to 2023, about half the citywide rate. https://commonsenseinstituteus.org/arizona/research/ballot-issues/arizona-prop-312/ - Goldwater Institute, "Goldwater Sues to Stop Phoenix's $7 Million Property Tax Shell Game" (May 6, 2022). Challenges Phoenix's use of a government property lease (GPLET) to let a downtown high-rise developer skip eight years of property tax, shifting the cost to other taxpayers, in violation of the state constitution's gift clause. https://www.goldwaterinstitute.org/?p=36407 - Common Sense Institute Arizona, Glenn Farley, "HB 2822 & The Taxation of Business Personal Property" (April 19, 2022). Business taxpayers hold less than 20% of property value but pay over 35% of property taxes, and a business with $500,000 of real property might pay $11,887 a year against $5,250 for a home of the same value; it adds that the Homeowner's Rebate, in which the state general fund pays 6% of all property tax payments to school districts, "potentially encourages residential property owners to favor higher property tax rates." https://commonsenseinstituteus.org/arizona/research/taxes-and-fees/hb-2822-the-taxation-of-business-personal-property/ - AZ Liberty Network (State Policy Network affiliate): no property tax report since 2021 was found. - Americans for Prosperity-Arizona: no property tax item since 2021 was found. Linked list: 10 items on the Analyses sheet (filter State = Arizona); every source URL is linked on the Sources sheet. | U4: 2012: Prop 117 replaced the old 10%/25% valuation rule with the 5% LPV cap (effective 2015). 2022: Legislature repealed the state equalization property tax (Laws 2022, ch. 317) and scheduled commercial assessment ratio cuts to 15% by FY2028 (Laws 2022, ch. 171); Homeowner's Rebate share raised to 50%. 2022-2025: AEL waivers for school districts passed by 2/3 votes (HCR 2039 for FY2022; HCR 2065 for FY2025; SCR 1041 for FY2026). Nov. 2024: Prop 312 approved (58.6%): owners may claim property tax refunds for costs caused when a city fails to enforce nuisance laws (illegal camping, loitering and similar). 2025 and 2026: Gov. Hobbs vetoed bills requiring bond and override pamphlets to show the tax effect on $100,000 and $300,000 homes (HB 2289 in 2026, a similar bill in 2025) and vetoed HB 2261 on agricultural valuation (2026). She signed Rep. Michael Carbone's expansion of the disabled veterans' exemption, effective for the 2026 tax year (Feb. 12, 2026). 2025 laws: SB 1224 (Laws 2025, ch. 96) resets limited value to the level of comparable property when a home loses the senior valuation freeze or a statutory valuation formula; SB 1122 (ch. 16) changed the inflation index for the widow, disability and veteran exemptions; SB 1700 (ch. 76) bars county boards of equalization from raising values above the assessor's notice. Nov. 3, 2026 ballot: eight legislative referrals, none of which changes property tax. Prop 316 (HCR 2021) would require voter approval for city and town taxes on food and cap them at 2% in aggregate; Prop 141 would bar taxes or fees based on miles driven. | V4: 4th (0.48% effective rate; 0.57% in 2010) | W4: Arizona is the only state with all four regimes in strong form: a 1980 constitutional spending limit (population plus inflation), a 2% levy limit on primary taxes, a 5% assessment cap with no reset on sale, and a 1% residential rate cap. The caveats: voters can and do override the spending limit, and the Legislature waives the school limit every year. Secondary taxes (bonds, overrides, special districts) sit outside the 1% and 2% caps. The 1% cap is enforced by a state subsidy (about $532 million in FY2026); local rates are never forced down. | X4: https://www.azleg.gov/const/9/18.htm https://www.azleg.gov/const/9/19.htm https://www.azleg.gov/const/9/20.htm https://www.azleg.gov/const/9/21.htm https://www.azleg.gov/ars/42/17107.htm https://www.azleg.gov/ars/16/00204.htm https://www.azleg.gov/ars/15/00972.htm https://www.azleg.gov/ars/41/01276.htm https://www.azleg.gov/ars/48/00807.htm https://www.azjlbc.gov/26AR/ade.pdf https://www.azjlbc.gov/units/tntletter080122.pdf https://www.azleg.gov/legtext/57leg/1R/summary/H.SCR1041_063025_TRANSMITTED.DOCX.htm https://azleg.gov/legtext/55leg/2R/summary/H.HCR2039_021522_TRANSMITTED.DOCX.htm https://www.azauditor.gov/resources/cities-and-towns/faqs https://mohave.gov/departments/assessor/program-enrollment/exemptions https://ballotpedia.org/Arizona_Property_Tax_Refund_for_Non-Enforcement_of_Public_Nuisance_Laws_Measure_(2024) https://taxfoundation.org/research/state-tax/2026-state-tax-ballot-measures/ https://apps.azsos.gov/election/2012/info/PubPamphlet/english/prop117.htm https://www.azleg.gov/ars/42/13302.htm https://www.kjzz.org/text/politics/2026-02-26/arizona-gov-katie-hobbs-vetoed-these-bills-in-2026 https://www.kjzz.org/politics/2026-02-13/bill-to-expand-property-tax-exemptions-for-disabled-veterans-passes-arizona-legislature https://www.goldwaterinstitute.org/yuma-county-hospital-district-treasurer-refunding-illegal-property-tax-after-goldwater-legal-challenge/ https://www.arizonatax.org/sites/default/files/publications/newsletters/file/ATRA%20Sept%20Oct%202026%20Newsletter.pdf https://azfree.org/blog/2025/12/04/arizonas-local-tax-trap-how-cities-are-destroying-affordability/ https://azfree.org/blog/2026/07/07/another-month-another-onslaught-of-municipal-tax-and-fee-increases/ https://www.cavanaghlaw.com/post/arizona-salt-newsletter-vol-15-summary-of-2025-arizona-tax-legislation https://www.azmed.org/eight-statewide-ballot-measures-set-for-arizonas-november-election
A5: Arkansas | B5: C. Restriction points 8.5 of 18 (levy limit 2; assessment cap 2; rate cap 2; rollback 1; school districts covered 1; use restrictions 0.5). Deductions: built-in loopholes -1; workarounds in practice -0.5; state buydowns -1.5; data record +0. Total 5.5 = C (A 11+, B 8.5-10.9, C 5.5-8.4, D 3-5.4, F under 3). Why: Built-in loopholes -1: the 10% revenue rollback works only in reappraisal years and excludes new construction, school millage has a 25-mill floor and no ceiling, and millage may rise to meet debt service. Workarounds -0.5: local governments lean on sales taxes (58.9% of local tax revenue) and keep putting new sales taxes to voters (Fayetteville, El Dorado, 2026). Buydowns -1.5: the state-paid homestead credit, financed by a statewide sales tax, equaled roughly 8% to 9% of FY2024 state and local property tax. Record 0: a low level (1.62% of personal income; 0.52% effective rate) offsets fast growth (real per-person collections up 42.4% FY2002-FY2022, U.S. 23.4%; real homeowner bills up 26.8% 2010-2024, U.S. 9.3%). | C5: =((LEFT(D5,3)="Yes")+(LEFT(E5,3)="Yes")+(LEFT(F5,3)="Yes")+(LEFT(G5,3)="Yes"))&" of 4 in force"&IF(((LEFT(D5,7)="Partial")+(LEFT(E5,7)="Partial")+(LEFT(F5,7)="Partial")+(LEFT(G5,7)="Partial"))>0," + "&((LEFT(D5,7)="Partial")+(LEFT(E5,7)="Partial")+(LEFT(F5,7)="Partial")+(LEFT(G5,7)="Partial"))&" partial","")&CHAR(10)&CHAR(10)&IF(LEFT(D5,3)="Yes","✓",IF(LEFT(D5,7)="Partial","◐","✗"))&" Spending limit"&CHAR(10)&IF(LEFT(E5,3)="Yes","✓",IF(LEFT(E5,7)="Partial","◐","✗"))&" Levy limit"&CHAR(10)&IF(LEFT(F5,3)="Yes","✓",IF(LEFT(F5,7)="Partial","◐","✗"))&" Assessment cap"&CHAR(10)&IF(LEFT(G5,3)="Yes","✓",IF(LEFT(G5,7)="Partial","◐","✗"))&" Rate cap" | D5: No. No cap on growth in local budgets or appropriations. Counties, cities and school districts must balance their budgets, which is a balanced-budget rule and not a growth limit. (The "balanced budget amendment" cited in earlier versions of this matrix does not cap local spending growth.) | E5: Partial. Rollback-style levy cap after reappraisal only. When a countywide reappraisal raises a taxing unit's total assessed value by 10% or more (excluding new construction and newly discovered property), the unit must roll back its millage so that property tax revenue rises no more than 10% over the prior year. Tangible personal property and utility property are excluded from the calculation, and millage may be adjusted upward if needed to meet debt service. School maintenance-and-operation millage cannot fall below the 25-mill uniform rate of tax. Between reappraisals (every 3 or 5 years) there is no levy-growth limit. Authority: Ark. Const. amend. 59 (ratified 1980, 649,307 to 152,629), as modified by amend. 74 (1996) and amend. 79 (2000). | F5: Yes. After a countywide reappraisal, the assessed value of a homestead may rise no more than 5% a year, and other real property no more than 10% a year, until the reappraised value is reached. Excluded: newly discovered property, new construction and substantial improvements (25%+ of value). The limit carries no reset-on-sale rule; a transferred parcel is valued at the next countywide reappraisal. Homeowners who are 65+ or disabled have the assessed value of their homestead frozen (it can only fall). Assessment ratio: 20% of market value for all property. Authority: Ark. Const. amend. 79 (approved Nov. 2000); DFA Assessment Coordination Division. | G5: Yes. Constitutional millage caps by purpose. Counties: up to 21 mills (5 general, 5 bonded debt, 5 library operations, 3 library capital, 3 roads). Cities: up to 20 mills (5 general, 5 bonded debt, 5 library operations, 3 library capital, 1 police pension, 1 firefighter pension). School districts: a mandatory minimum of 25 mills for maintenance and operation and no maximum. Every levy except city and county general millage and county road millage requires voter approval, and all school millage changes require voter approval. Authority: Ark. Const. art. 12 §4 (cities) and art. 16 §9 (counties), with later amendments authorizing library, road and pension millage; amend. 74 (25-mill school minimum). | H5: Yes. School millage is covered by the reappraisal rollback (above the 25-mill floor), the Amendment 79 assessment caps and the homestead credit, and any change in school millage needs voter approval. Schools receive about 80% of property tax revenue in Arkansas (Association of Arkansas Counties). | I5: Yes. The 25-mill Uniform Rate of Tax (URT) for school maintenance and operation is set by the Constitution and levied in every school district. The revenue stays in the district and is counted as local revenue in the state foundation funding formula, so it works as a statewide school levy that offsets state aid. The Census Bureau classifies URT revenue as a state tax (about $1.32 billion in FY2022). Authority: Ark. Const. amend. 74 (1996). | J5: Partial. No homestead value exemption. Homeowners receive the state-funded Homestead Property Tax Credit instead (see Credits), plus the Amendment 79 5% assessment cap and the 65+/disabled freeze. Disabled veterans (and certain surviving spouses) are fully exempt on their homestead. Authority: Ark. Const. amend. 79; Ark. Code Ann. §26-26-1118. | K5: Yes. Homestead Property Tax Credit: a flat credit on the tax bill of every owner-occupied homestead. It has risen from $300 (2000) to $350, $375, $425 (2023), $500 (2024) and $600 (SB 263 of 2025, first applied to 2026 tax bills). The 2026 fiscal session raised it to $675 (HB 1103, Act 174 of 2026; DFA cost $39.8 million in 2027). Authority: Ark. Code Ann. §26-26-1118. | L5: Yes. The homestead property tax credit reduces the real property tax bill on every homestead, and the state reimburses counties for the credits from the Property Tax Relief Trust Fund, which is funded by a statewide half-cent sales tax enacted in 2000 with Amendment 79. Act 330 of 2025 raised the credit from $500 to $600, and Act 174 of 2026 raised it to $675 for assessment years beginning in 2026. DFA estimates the latest increase adds $39.8 million in credits in 2027. Authority: Ark. Const. amend. 79; Ark. Code Ann. §§ 26-26-1118, 26-26-310; Act 330 of 2025; Act 174 of 2026; DFA Fiscal Impact Statement, HB1103 (2026). | M5: No. | N5: Yes. Mandatory millage rollback after countywide reappraisal when assessed value rises 10% or more (see Levy limit); revenue growth from reappraisal is limited to 10%. No rollback between reappraisals. | O5: No. Millage questions pass by simple majority of voters. Quorum courts and city councils set general and county road millage within the caps by ordinary vote. | P5: No. School millage changes are usually decided at the annual school election, now held in March (Act 503 of 2025), or at special elections; city and county millage questions can go on general or special election ballots. | Q5: Yes. Constitutional millage is earmarked by purpose: county and city general, bonded debt, library operations, library capital, county roads, police and firefighter pensions. School millage is dedicated to maintenance and operation or to debt service as approved by voters. Money from a dedicated levy may not be used for other purposes. | R5: 75 counties; 500 municipalities; 234 school districts (all levy the 25-mill URT); improvement districts, fire protection districts, levee and drainage districts, and similar special districts, many of which are funded by benefit assessments and fees and levy no ad valorem millage. Census of Governments 2022: 1,562 local governments, including 753 special districts (173 drainage/flood control, 72 fire protection, 17 library). | S5: Verdict: Failed. Property tax per person rose 48.5% after inflation from FY2002 to FY2024, against 25.9% for the U.S., though growth slowed to 0.3% from FY2019 to FY2024. Why it leaks: The Amendment 59 rollback applies only after a countywide reappraisal and still lets revenue rise 10%, and between reappraisals no levy limit applies. New construction falls outside the rollback. School millage has a 25-mill floor and no ceiling. The homestead credit, paid from a statewide half-cent sales tax, lets local governments keep every dollar, a subsidy that counts against Arkansas. How localities get around it: School districts send millage questions to the annual school election, now held in March under Act 503 of 2025, or to special elections. Fayetteville asked voters in March 2026 to renew a 1% sales tax for water and wastewater bonds. Full record: Has it worked? The tax stays low, but collections per person grew 48.5% after inflation from FY2002 to FY2024, the 6th-fastest of 50 (U.S. +25.9%); part of the homeowner's bill is paid with state sales tax. The record (Census, BEA, ACS): state and local property tax was $961 per person in FY2024 (U.S. $2,132), 1.62% of personal income (47th-highest of 50; U.S. 2.89%). After inflation, collections per person (all state and local property tax divided by residents) rose 48.5% from FY2002 to FY2024 (U.S. +25.9%) and rose 0.3% from FY2019 to FY2024 (U.S. -1.1%). The median homeowner paid $1,113 in 2024 (U.S. $3,211); the median bill rose 26.8% after inflation from 2010 to 2024 (U.S. +9.3%). The Tax Foundation's 2026 ranking puts its effective property tax rate on owner-occupied homes at 0.56%, 14th-lowest of 50. By the same measure it was 0.56% in 2010 (U.S. 1.00% in 2010, 0.94% in 2024). Local officials need voter approval for nearly every millage increase. Caveats: Shift to sales tax: local governments lean on sales taxes far more than property taxes. Sales taxes supply 58.9% of local tax revenue and property taxes 39.5% (Census, FY2022, which counts the URT as a state tax). Arkansas's average combined sales tax rate is 9.46%, 4th-highest in the country. Relief paid by sales tax: the main homeowner relief (the homestead credit, $600 on 2026 bills and $675 under Act 174 of 2026) is financed by a statewide half-cent sales tax, so homeowners' bills fall while local governments keep every dollar. DFA prices each $100 of credit at about $53 million to $56 million a year, so the credit cost roughly $225 million to $265 million a year at the $425-$500 levels in force during FY2024, about 8% to 9% of state and local property tax collections. The Legislature has also dipped into the relief fund's surplus for other projects. TIF and Issue 3: Issue 3 on the Nov. 3, 2026 ballot would exempt property in new economic development districts from regular school, county and city property taxes and let the districts tax it themselves, reopening the school tax base to tax increment financing that the Arkansas Supreme Court closed in 2007. Sales tax votes: local governments keep asking voters for new or renewed sales taxes. In March 2026 Fayetteville asked voters to renew a 1% sales tax backing up to $150.5 million in water and wastewater bonds, and El Dorado sought a permanent 0.5% sales tax for its regional hospital (University of Arkansas Cooperative Extension, Jan. 12, 2026). Reappraisal timing: the 10% revenue rollback applies only in reappraisal years; growth from new construction and between reappraisals is uncapped. | T5: - Arkansas Senate (Republican majority), "Lawmakers Discuss Issue 3" (Aug. 21, 2026). Sen. Jonathan Dismang presented SJR 15, Issue 3 on the November ballot, to the Joint City, County and Local Affairs Committee: property inside a new economic development district would be exempt from most taxes except those the district levies, and bonds backed by property taxes for these projects would still need local voter approval. Local officials described it as a local-control tool to compete with neighboring states' incentives; it would take effect January 1, 2027. https://senate.arkansas.gov/senate-news/posts/2026/08/lawmakers-discuss-issue-3/ - Arkansas House of Representatives (Republican majority), "2026 Fiscal Session Week 3" (April 24, 2026). Reports that the House Revenue and Tax Committee advanced HB 1103 to raise the Homestead Property Tax Credit from $600 to $675 for assessment years beginning Jan. 1, 2026, alongside a $6.7 billion budget up $211 million and a projected $310.2 million surplus at the end of FY2027. https://www.arkansashouse.org/?p=33676 - Tax Foundation (national), Jared Walczak, "Property Tax Limitation Regimes: A Primer" (April 2, 2025). Explains the three limit types: assessment limits shield individual owners but create unequal burdens among similar properties, rate limits do not stop increases from rising values, and levy limits restrain total revenue growth. Its table credits Arkansas with all three, and it warns that any limit can shift taxes to other local sources or to the state. https://taxfoundation.org/research/all/state/property-tax-limitation-regimes-primer/ - Arkansas Senate (Republican majority), "Senate Passes Additional $100 a Year Property Tax Credit" (March 12, 2025). SB 263 raises the homestead property tax credit from $500 to $600 a year starting in 2026, which the Senate says saves about 708,000 homeowners $56 million a year. https://senate.arkansas.gov/senate-news/posts/2025/03/9926-2/ - Arkansas Policy Foundation, "ARKANSAS INCOME TAX RATE CUT TO 3.9%" (June 10, 2024). The only property tax item found on its site since 2021; it reports that Gov. Sarah Huckabee Sanders signed measures on June 19, 2024 that cut the top income tax rate to 3.9% and used surplus revenue to raise the homestead property tax credit from $425 to $500 for assessment years beginning Jan. 1, 2024. Its other recent tax work covers income tax cuts. https://arkansaspolicyfoundation.org/arkansas-income-tax-rate-cut-to-3-9/ - Opportunity Arkansas Foundation (State Policy Network affiliate): no property tax report since 2021 was found; its site blocks automated searches. - Advance Arkansas Institute: no property tax report since 2021 was found. - Americans for Prosperity-Arkansas: no property tax item since 2021 was found. Linked list: 5 items on the Analyses sheet (filter State = Arkansas); every source URL is linked on the Sources sheet. | U5: 2023: homestead credit $375 -> $425. 2024: $500. 2025: $600 (SB 263, Act 330 of 2025, signed March 18, 2025; $56 million a year; first applied to 2026 bills). Other 2025 acts: disabled veterans' homestead exemption extended from 40 to 160 acres (Act 407); annual notice to every taxpayer of 65+ and disability relief (Act 877). 2026 fiscal session: HB 1103 raised the credit to $675 (94-0 in the House; became Act 174 on May 1, 2026; DFA cost $39.8 million in 2027). 2025: Act 503 moved annual school elections (where most school millage questions appear) to March. Nov. 3, 2026 ballot: Issue 3 (SJR 15 of 2025, referred by the Legislature in April 2025) would let the Legislature create economic development districts inside cities, counties or cooperative areas; property in a district would be exempt from school, county, city and other property taxes, and the district could levy its own taxes, assessments and fees. Local bonds for these projects repaid with property taxes would need voter approval. It would supersede the 2007 Arkansas Supreme Court ruling that kept tax increment financing from capturing the 25-mill school tax (University of Arkansas Public Policy Center). Issues 1, 2 and 4 (voter eligibility, the right to bear arms, $500 million in water and pollution bonds) do not concern property tax. 2025: SJR 16 (Sen. Crowell), a proposed amendment on property taxes, was withdrawn and sent to interim study. A 2000-era petition drive to abolish property taxes failed to make the ballot and produced Amendment 79 instead. | V5: 14th (0.56% effective rate; 0.56% in 2010) | W5: Arkansas combines constitutional millage caps, a 5%/10% assessment cap with a senior freeze, a 10% reappraisal rollback and a statewide 25-mill school levy. It has no spending cap and no truth-in-taxation law. Its signature relief, the homestead credit, is a state subsidy financed by a half-cent sales tax, which helps explain why Arkansas has one of the nation's heaviest sales tax burdens. | X5: https://www.uaex.uada.edu/publications/PDF/fsppc114.pdf https://www.dfa.arkansas.gov/office/arkansas-assessment-coordination-division/real-property/property-tax-relief https://encyclopediaofarkansas.net/entries/amendment-59-9041/ https://www.lincolninst.edu/sites/default/files/gwipp/upload/sources/Arkansas/2006/amendment79_assessors-guide.pdf https://regfollower.com/us-arkansas-increases-property-tax-credit-raises-homestead-property-tax-credit-by-usd-100/ https://www.myarklamiss.com/www-myarklamiss-com-news-south-arkansas/legislation-increasing-homestead-property-tax-credit-passed-by-legislature-heads-to-arkansas-gov-sarah-huckabee-sanders-desk/amp/ https://arcounties.org/media/articles/homestead-tax-credit-has-always-been-priority https://ezel.ai/ag-opinions/ar/2026-006-question-1-under-current-arkansas-law-when-can-the-annual-sc https://www.lincolninst.edu/app/uploads/2025/01/levy_limits_2022.xlsx https://www2.census.gov/programs-surveys/gov-finances/tables/2022/22slsstab1.xlsx https://arkleg.state.ar.us/Bills/Detail?id=HB1103&ddBienniumSession=2025%2F2026F https://www.dfa.arkansas.gov/wp-content/uploads/AACD_AnnualReport_2025.pdf https://uaex.uada.edu/business-communities/voter-education/issue3.aspx https://www.uaex.uada.edu/media-resources/news/2026/october/10-07-2026-ark-ballot-guide-26.aspx https://www.uaex.uada.edu/business-communities/ced-blog/posts/2026/january/arkansas-voters-have-local-ballot-issues-to-decide-march-2026-election.aspx https://www.arkansashouse.org/?p=33676 https://policyrisk.com/state-bill/AR-SJR16-2025
A6: California | B6: D. Restriction points 10.75 of 18 (spending limit 4; assessment cap 2; rate cap 2; supermajority 1; school districts covered 1; November-ballot rule 0.25; use restrictions 0.5). Deductions: built-in loopholes -2; workarounds in practice -3; state buydowns +0; data record -1. Total 4.75 = D (A 11+, B 8.5-10.9, C 5.5-8.4, D 3-5.4, F under 3). Why: Built-in loopholes -2: parcel taxes, Mello-Roos taxes and assessments sit outside the 1% cap; school bonds need only 55%; the Upland ruling lets citizen-initiated special taxes pass by simple majority; the Gann limit excludes debt service and capital outlay and voters can raise it. Workarounds -3: pervasive and led by the largest cities, including Los Angeles's majority-vote Measure ULA ($1.03 billion by Jan. 2026), 90 of 125 local tax measures passed in 2024, sales tax rates above 10% and fees at 42% of local own-source revenue. Buydowns 0: the homeowners' exemption subvention is far below 5% of collections. Record -1: real per-person collections up 51.1% FY2002-FY2022 (U.S. 23.4%) and 8.7% FY2019-FY2024 (U.S. -1.1%); real homeowner bills up 29.5% 2010-2024 (U.S. 9.3%). | C6: =((LEFT(D6,3)="Yes")+(LEFT(E6,3)="Yes")+(LEFT(F6,3)="Yes")+(LEFT(G6,3)="Yes"))&" of 4 in force"&IF(((LEFT(D6,7)="Partial")+(LEFT(E6,7)="Partial")+(LEFT(F6,7)="Partial")+(LEFT(G6,7)="Partial"))>0," + "&((LEFT(D6,7)="Partial")+(LEFT(E6,7)="Partial")+(LEFT(F6,7)="Partial")+(LEFT(G6,7)="Partial"))&" partial","")&CHAR(10)&CHAR(10)&IF(LEFT(D6,3)="Yes","✓",IF(LEFT(D6,7)="Partial","◐","✗"))&" Spending limit"&CHAR(10)&IF(LEFT(E6,3)="Yes","✓",IF(LEFT(E6,7)="Partial","◐","✗"))&" Levy limit"&CHAR(10)&IF(LEFT(F6,3)="Yes","✓",IF(LEFT(F6,7)="Partial","◐","✗"))&" Assessment cap"&CHAR(10)&IF(LEFT(G6,3)="Yes","✓",IF(LEFT(G6,7)="Partial","◐","✗"))&" Rate cap" | D6: Yes. Gann Limit (Prop 4, Nov. 1979): an annual appropriations limit on the state and every city, county, school district and special district. Appropriations of tax proceeds may grow each year only by population growth times a cost-of-living factor (Prop 111 of 1990 let localities choose per-capita personal income or the change in nonresidential new construction, and county or city population). Revenue above the limit over two years must be returned. Excluded: debt service, federal mandates, court-ordered costs, qualified capital outlay, user fees not exceeding cost, and other items. Local voters may raise an agency's limit for up to four years at a time; cities and special districts periodically put such "appropriations limit" increases on the ballot. Authority: Cal. Const. art. XIII B (Prop 4, 1979; amended by Prop 111, 1990). | E6: No. No cap on the growth of total property tax collections. The combination of the 1% rate cap and the 2% assessment cap restrains growth on existing parcels, but revenue rises with each sale, new construction and voter-approved debt or special taxes. The 1% levy is allocated among local agencies by state formula (AB 8 of 1979), so local governments cannot raise it. | F6: Yes. Acquisition-value assessment: property is taxed on its 1975-76 value or its value at the most recent change in ownership or new construction, increased each year by the lesser of 2% or CPI. Sale or other change in ownership resets value to market. Not treated as a change in ownership / no reassessment: transfers between spouses; transfers into revocable trusts; the family home passed to a child or grandchild who lives in it (excluded value capped at taxable value plus about $1 million, indexed; Prop 19 of 2020 narrowed the older, broader parent-child and grandparent exclusions); base-year value transfers for owners 55+, severely disabled owners and disaster victims, now statewide and up to three times (Prop 19); transfers of interests in legal entities unless control (over 50%) changes. New construction exclusions: active solar systems, seismic retrofits, fire sprinklers, disabled-access improvements and rebuilding after a disaster. Authority: Cal. Const. art. XIII A §2 (Prop 13, June 1978, 64.8% yes); Props 58 (1986), 193 (1996), 60/90 (1986/1988), 19 (2020); Rev. & Tax. Code §§60-69.5. | G6: Yes. Ad valorem tax may not exceed 1% of assessed value, plus rates to repay voter-approved debt. Debt rates require 2/3 voter approval for cities, counties and special districts and 55% for school and community college construction bonds (Prop 39, 2000); statewide, debt rates add roughly 0.1% of assessed value on average (LAO). Parcel taxes, Mello-Roos special taxes and benefit assessments are not ad valorem and sit outside the 1% cap. Authority: Cal. Const. art. XIII A §1 (Prop 13, 1978); Prop 46 (1986); Prop 39 (2000). | H6: Yes. School districts receive the largest share of the 1% levy and are subject to the same 1% and 2% limits and the Gann Limit. Because Prop 98 guarantees a minimum school funding level, property tax growth for schools mainly reduces state aid; the state also diverted city, county and special-district property taxes to schools through the Educational Revenue Augmentation Fund (ERAF) starting in 1992-93. School bonds need only 55%, and school parcel taxes 2/3. | I6: No. The state levies no property tax. All ad valorem revenue is local, but the Legislature controls how the 1% levy is divided among roughly 4,000 local agencies (AB 8 of 1979, ERAF shifts, the 2004 "triple flip" and VLF swap). Constitutional amendments (Prop 1A of 2004, Prop 22 of 2010) now restrict further state shifts. | J6: Yes. Homeowners' Exemption: $7,000 of assessed value on a principal residence (about $70 a year in tax). The amount has not changed since 1974, and the state must reimburse local governments for the revenue loss. Disabled veterans' exemption: basic and low-income amounts indexed annually (2026: $180,671 basic and $271,009 low-income, with a household income limit of $81,131; Board of Equalization). Authority: Cal. Const. art. XIII §3(k); Rev. & Tax. Code §§218, 205.5. | K6: Partial. No circuit breaker. A small nonrefundable income tax renter's credit ($60 single, $120 joint, income-limited) and the Senior Citizens' Property Tax Postponement program (state-funded deferral for low-income owners 62+, blind or disabled) are the only bill-side programs. | L6: Yes. The Constitution exempts the first $7,000 of assessed value of every owner-occupied principal residence and requires the state to reimburse local agencies for the revenue lost. The Homeowners' Property Tax Relief subvention is $420.0 million in 2025-26 and $410.0 million in the 2026-27 enacted budget. Williamson Act open-space subventions remain in law but receive a nominal $1,000. Proposition 98 school funding is general school aid and does not count. Authority: Cal. Const. art. XIII, §§ 3(k), 25; Rev. & Tax. Code § 218; Gov. Code §§ 16120-16122; 2026-27 Enacted Budget, 9100 Tax Relief. | M6: No. | N6: No. No rollback rule. The fixed 1% rate and 2% assessment cap make one unnecessary for the general levy; debt-service rates move with bond costs. | O6: Yes. Voters: local special taxes (dedicated to a purpose, including parcel taxes and Mello-Roos taxes) need 2/3; local general obligation bonds 2/3; school bonds 55%; general taxes a majority. Since Cal. Cannabis Coalition v. City of Upland (2017) and follow-on appellate rulings, special taxes placed on the ballot by citizen initiative pass by simple majority. Legislature: 2/3 of each house for state tax increases (Prop 13 §3, as broadened by Prop 26 of 2010). Prop 43 (Nov. 2026) would restore 2/3 for citizen-initiated local special taxes starting Jan. 1, 2027. Authority: Cal. Const. art. XIII A §§3-4; art. XIII C §2 (Prop 218, 1996); art. XVI §18. | P6: Partial. A local general tax increase must be submitted at a regularly scheduled general election for members of the governing body, unless the body unanimously declares an emergency. Special taxes and bonds may go on special or regular election ballots. Authority: Cal. Const. art. XIII C §2(b) (Prop 218, 1996). | Q6: Yes. Special taxes, parcel taxes and Mello-Roos taxes may fund only the purposes stated on the ballot; bond proceeds only the listed projects. Prop 218 limits property-related fees (water, sewer, refuse) to the cost of the service, and assessments to special benefit. The 1% general levy is unrestricted for the agencies that receive it. | R6: 58 counties (San Francisco is a consolidated city-county); 482 cities; 1,006 independent school districts and 72 community college districts; 2,949 special districts in the Census count (354 fire, 341 water, 248 cemetery, 148 park and recreation, plus hospital, library, mosquito-abatement, irrigation and others), many of which receive a share of the 1% levy; plus Mello-Roos community facilities districts and assessment districts that levy special taxes or assessments. Census of Governments 2022: 4,494 local governments. | S6: Verdict: Failed. Property tax per person rose 64.8% after inflation from FY2002 to FY2024, against 25.9% for the U.S. Why it leaks: Prop 13 caps the rate at 1% and yearly assessment growth at 2%, yet California has no levy limit, so each sale resets value to market and new construction adds to the rolls. Parcel taxes and Mello-Roos special taxes sit outside the 1% cap, and voter-approved debt rates float each year with no new vote. School bonds need only 55% (Prop 39, 2000). Since the 2017 Upland ruling, citizen-initiated special taxes pass by simple majority. How localities get around it: Landowner-developers approve Mello-Roos taxes on new subdivisions before buyers arrive. Los Angeles Measure ULA, a 2022 transfer tax passed by simple majority under Upland, raised more than $1.03 billion by Jan. 8, 2026. Full record: Has it worked? For long-time owners, yes: the 1% rate cap and the 2% assessment cap have held since 1978. For total property taxes, no: collections per person grew 64.8% after inflation from FY2002 to FY2024, third-fastest of 50 behind Hawaii and New Mexico. The record (Census, BEA, ACS): state and local property tax was $2,492 per person in FY2024 (U.S. $2,132), 2.87% of personal income (21st-highest of 50; U.S. 2.89%). After inflation, collections per person (all state and local property tax divided by residents) rose 64.8% from FY2002 to FY2024 (U.S. +25.9%) and rose 8.7% from FY2019 to FY2024 (U.S. -1.1%). The median homeowner paid $5,369 in 2024 (U.S. $3,211); the median bill rose 29.5% after inflation from 2010 to 2024 (U.S. +9.3%). The Tax Foundation's 2026 ranking puts its effective property tax rate on owner-occupied homes at 0.70%, 19th-lowest of 50. By the same measure it was 0.69% in 2010 (U.S. 1.00% in 2010, 0.94% in 2024). The FY2024 Census figure is a sample estimate with a 24% coefficient of variation. Collections reached about $97.9 billion in 2023-24 (Board of Equalization). Why: the 2% cap limits each parcel, but revenue still grows through reassessment at sale, new construction and voter-approved debt and special taxes outside the 1%. When CPI rose 7.27% in 2022, the cap held the inflation factor at 2% (Board of Equalization), so the growth came from those channels. California is the case study in working around limits: Workarounds: (1) Mello-Roos special taxes on new subdivisions, often approved by landowner-developers before buyers arrive; (2) school parcel taxes and 55% school bonds; (3) the Upland decision, which lets activist-written special taxes pass by majority (e.g., San Francisco's 2018 Prop C business tax; Los Angeles Measure ULA "mansion tax," 2022); (4) relabeling taxes as fees until Prop 218 (1996) and Prop 26 (2010) tightened definitions; (5) the state's own ERAF shifts of local property taxes to schools to cut state costs; (6) Prop 19 (2020), sold as senior portability, also narrowed the parent-child exclusion, raising reassessments. Los Angeles: Measure ULA, the 2022 citizen-initiated transfer tax that passed by simple majority under the Upland ruling, had raised more than $1.03 billion from 1,435 sales by Jan. 8, 2026, including $413.2 million in FY2025; it adds 4% on sales from $5.3 million to $10.6 million and 5.5% above that (Commercial Observer, Jan. 12, 2026, from Los Angeles Housing Department data). Los Angeles voters will also decide in November whether to raise the city's sales tax from 9.75% to 10.25% (Pacific Research Institute). Local tax measures: 125 local tax measures went on ballots in 2024 and 90 passed (Howard Jarvis Taxpayers Association, cited by the Pacific Research Institute). Nov. 2026 ballots add a half-cent sales tax in San Diego County, a one-cent increase in the city of Orange and transit taxes in five Bay Area counties and San Francisco; several cities already exceed a 10% combined sales tax rate. Revenue shift: local sales tax add-ons are routine (the combined rate averages 8.99%, 7th-highest); fees and charges supply 42% of local own-source revenue vs. 34% nationally; property tax is 66.7% of local taxes (Census FY2022). Inequity: identical homes can carry very different bills (new buyers in Los Angeles pay a 53% premium), the lock-in effect cited even by Prop 13's defenders. | T6: - Howard Jarvis Taxpayers Association, Scott Kaufman, "UNDER THE DOME: THE INSIDE STORY ON THE DEAL TO SAVE PROP. 13" (Sept. 21, 2026). HJTA refused to withdraw its Save Proposition 13 initiative in exchange for a statutory transfer tax cap (AB 736) and won a deal: on June 25 the Legislature passed ACA 22, now Prop 43, which requires two-thirds voter approval for all new local special taxes and closes the Upland loophole, plus ACA 21 to pull the ACA 13 "poison pill" off the November ballot. In return HJTA deferred the transfer tax fight and gave up a provision that would have repealed some existing transfer and parcel taxes passed through court-created loopholes. https://www.hjta.org/news-events/taxing-times/taxing-times-online-fall-2026-vol-52-issue-3/under-the-dome-the-inside-story-on-the-deal-to-save-prop-13/ - California Policy Center, "CPC’s 2026 Voter Information Guide" (Sept. 25, 2026). CPC's take is YES on Prop 43, which it says "closes a loophole that allows local government unions to raise taxes without complying with Proposition 13" and also bars new ad valorem property taxes above Prop 13's 1% base rate. CPC is also YES on Props 41 and 42 and NO on Prop 2, which would double the rainy day fund cap to 20% of General Fund tax revenue and exclude deposits from the Gann spending limit. https://californiapolicycenter.org/cpcs-2026-voter-information-guide/ - California Taxpayers Association (CalTax), "California Voters Will See 273 Tax Increases on Local Ballots in November" (Sept. 3, 2026). November local ballots carry 273 tax measures: $3 billion in direct taxes plus $19.5 billion in bonds repaid through property taxes above Prop 13's 1% limit. Seventy are parcel taxes and 82 are school bonds; nine use the Upland loophole, and CalTax says the bonds would cost property owners more than $1.15 billion a year (projections for 76 measures). https://caltax.org/news-release/california-voters-will-see-273-tax-increases-on-local-ballots-in-november/ - Pacific Research Institute, Kerry Jackson, "Another Tax That Backfired" (March 10, 2026). Los Angeles' Measure ULA "mansion tax" (4% on sales above $5.3 million, 5.5% above $10.6 million) raised $1.09 billion in three years from fewer than 1,500 sales, less than the $1.1 billion backers promised for a single year. Cites a university paper estimating ULA cut eligible transactions 38% and that "at least 63 percent, and potentially over 100 percent" of its revenue is offset by lower future property tax collections. https://www.pacificresearch.org/another-tax-that-backfired/ - Pacific Research Institute, Wayne Winegarden, "Spending Watch: Californians Will Pay a High Price for Tom Steyer’s “Split-Role” Proposal" (March 2, 2026). Opposes gubernatorial candidate Tom Steyer's plan to remove Prop 13 limits on commercial property, calling Prop 13 "one of the few protections that taxpayers have against ever-rising taxes in the state." Using the LAO's 2020 estimate of $8.0 billion to $12.5 billion in new revenue, PRI's model projects a 3.4% to 4.8% smaller state economy within five years and up to 322,000 fewer jobs. https://www.pacificresearch.org/spending-watch-californians-will-pay-a-high-price-for-tom-steyers-split-role-proposal/ - Pacific Legal Foundation, "Pacific Legal Foundation applauds California’s move to end home equity theft loophole" (Oct. 3, 2025). Praises AB 418, signed Oct. 1, 2025, which closes a loophole that let California localities take homes from owners behind on property taxes and transfer them to the government or nonprofits without refunding surplus equity. PLF ties the law to its 2023 U.S. Supreme Court win in Tyler v. Hennepin County. https://pacificlegal.org/press-release/pacific-legal-foundation-applauds-californias-move-to-end-home-equity-theft-loophole/ - California Policy Center, Edward Ring, "California’s Unstoppable Taxation Machine" (Oct. 24, 2024). Argues Prop 13's two-thirds vote rules have been "slowly undermined" over the years and faults the state Supreme Court for removing the Taxpayer Protection and Government Accountability Act from the 2024 ballot. It also attacks two legislative counter-measures: Prop 5, cutting the vote for local housing and infrastructure bonds to 55%, and ACA 13, which would make initiatives that raise vote thresholds pass by the same supermajority (ACA 13 was later pulled from the 2026 ballot under the HJTA deal above). https://californiapolicycenter.org/californias-unstoppable-taxation-machine/ - Reason Foundation, Adrian Moore, "California Proposition 5 would lower supermajority requirement to 55% for local bond measures to fund housing and public infrastructure amendment" (Sept. 24, 2024). Explains that Prop 5 would carve an exception to the Prop 13 and Prop 218 two-thirds rule for local housing and infrastructure debt. Notes counties carried about $140 billion in liabilities ($3,860 per resident) and cities $193 billion ($6,337) as of 2023, with $29.8 billion more borrowed in early 2024, and concludes "it seems governments are not having trouble getting voter approval for new debt or finding lenders." https://reason.org/voters-guide/california-proposition-5-lower-supermajority-requirement-to-55-for-local-bond-measures-to-fund-housing-and-public-infrastructure-amendment/ - California Taxpayers Association (CalTax), "Proposition 13 Protects Property Owners From 7 Percent Tax Hike in 2023" (Jan. 6, 2023). With California CPI up 7.27%, Prop 13 held the annual inflation factor on assessed values to 2%, keeping bills "stable and predictable." https://caltax.org/2023/01/06/proposition-13-protects-property-owners-from-7-percent-tax-hike-in-2023/ - Independent Institute (State Policy Network associate): no California property tax report since 2021 was found. Linked list: 14 items on the Analyses sheet (filter State = California); every source URL is linked on the Sources sheet. | U6: 2020: Prop 15 ("split roll" to reassess commercial property at market value) failed (48.0% yes); Prop 19 passed (51.1%). 2022: Los Angeles Measure ULA transfer tax on sales over $5 million passed by majority as a citizen-initiated special tax. 2024: the California Supreme Court removed the Taxpayer Protection and Government Accountability Act (which would have required 2/3 for citizen-initiated special taxes and tightened fee rules) from the ballot (Legislature v. Weber); Prop 5, lowering the vote for local housing and infrastructure bonds to 55%, failed. May 2025: the Howard Jarvis Taxpayers Association filed the "Save Proposition 13 Act of 2026" to reverse the Upland ruling. June 25, 2026: the Legislature passed ACA 22, a narrower measure restoring the two-thirds vote for local special taxes (now Prop 43), and ACA 21, which removed ACA 13 from the November ballot; HJTA then withdrew its initiative (HJTA, Taxing Times, Sept. 21, 2026). Nov. 2026 ballot: Prop 43 (2/3 vote for citizen-initiated local special taxes), Prop 41 (new state taxes may not escape the Gann Limit), Prop 40 (one-time 5% billionaire wealth tax), Prop 3 (make 2012 income tax surcharge permanent), Prop 42 (bars new state taxes on the ownership of financial assets or other personal property and certain retroactive state taxes), Prop 1 (state housing bonds). The California Policy Center reads Prop 43 as also barring new ad valorem property taxes above Prop 13's 1% rate. | V6: 19th (0.70% effective rate; 0.69% in 2010) | W6: California pairs a strict 1% rate cap and 2% acquisition-value assessment cap (Prop 13) with a spending limit (Gann) and 2/3 voter thresholds for special taxes. The limits hold for existing homeowners, but governments have shifted costs onto new buyers (Mello-Roos, reassessment on sale), parcel taxes, fees and sales taxes, and courts opened a majority-vote path for citizen-initiated special taxes, which Prop 43 on the Nov. 2026 ballot would close. | X6: https://lao.ca.gov/reports/2012/tax/property-tax-primer-112912.pdf https://lao.ca.gov/BallotAnalysis/Proposition?number=43&year=2026 https://lao.ca.gov/BallotAnalysis/Propositions https://www.boe.ca.gov/proptaxes/dv_exemption.htm https://ebudget.ca.gov/2016-17/Enacted/StateAgencyBudgets/8000/9100/program_description_7500.html https://leginfo.legislature.ca.gov/faces/codes_displayText.xhtml?lawCode=CONS&article=XIII%20A https://leginfo.legislature.ca.gov/faces/codes_displayText.xhtml?lawCode=CONS&article=XIII%20B https://leginfo.legislature.ca.gov/faces/codes_displayText.xhtml?lawCode=CONS&article=XIII%20C https://www.lincolninst.edu/app/uploads/2024/12/assessment_limits_2022-3.xlsx https://taxfoundation.org/research/all/state/property-tax-limitation-regimes-primer/ https://taxfoundation.org/research/state-tax/2026-state-tax-ballot-measures/ https://leginfo.legislature.ca.gov/faces/codes_displayText.xhtml?lawCode=CONS&division=&title=&part=&chapter=&article=13A https://caltax.org/2025/04/25/california-property-tax-revenue-increased-8-9-billion-in-2024-boe-reports/ https://www.hjta.org/press-releases/new-initiative-to-save-proposition-13/ https://calmatters.org/politics/2026/10/california-prop-43-election-2026/ https://www.boe.ca.gov/proptaxes/pdf/lta25014.pdf https://commercialobserver.com/2026/01/measure-ula-revenue-billion/ https://www.pacificresearch.org/california-cities-turn-to-tax-hikes-to-deal-with-overspending/ https://californiapolicycenter.org/cpcs-2026-voter-information-guide/ https://www.hjta.org/news-events/taxing-times/taxing-times-online-fall-2026-vol-52-issue-3/under-the-dome-the-inside-story-on-the-deal-to-save-prop-13/
A7: Colorado | B7: C. Restriction points 13.25 of 18 (spending limit 4; levy limit 4; assessment cap 1; rate cap 2; rollback 0.5; school districts covered 1; November-ballot rule 0.5; use restrictions 0.25). Deductions: built-in loopholes -3; workarounds in practice -2; state buydowns +0; data record -1. Total 7.25 = C (A 11+, B 8.5-10.9, C 5.5-8.4, D 3-5.4, F under 3). Why: Built-in loopholes -3: voters may waive TABOR's revenue limit and nearly every county, most cities and most school districts have (Arapahoe and Jefferson in 2024); home-rule cities and school districts are excluded from the 2024 statutory levy limit; fee-funded enterprises sit outside TABOR. Workarounds -2: de-Bruced governments held mill levies flat through the 2023 reappraisal and raised bills without a vote, and more than 2,300 developer-run metro districts levy mills on new homeowners. Buydowns 0: state reimbursement of the senior exemption and 2022-2024 backfills appear to be below 5% of the $14.25 billion FY2024 total (not confirmed). Record -1: real growth per person of 40.3% (FY2002-FY2022, U.S. 23.4%) and 7.8% (FY2019-FY2024, U.S. -1.1%), and real homeowner bill growth of 36% (2010-2024, U.S. 9.3%, 49th), offset only partly by a low 0.49% effective rate. | C7: =((LEFT(D7,3)="Yes")+(LEFT(E7,3)="Yes")+(LEFT(F7,3)="Yes")+(LEFT(G7,3)="Yes"))&" of 4 in force"&IF(((LEFT(D7,7)="Partial")+(LEFT(E7,7)="Partial")+(LEFT(F7,7)="Partial")+(LEFT(G7,7)="Partial"))>0," + "&((LEFT(D7,7)="Partial")+(LEFT(E7,7)="Partial")+(LEFT(F7,7)="Partial")+(LEFT(G7,7)="Partial"))&" partial","")&CHAR(10)&CHAR(10)&IF(LEFT(D7,3)="Yes","✓",IF(LEFT(D7,7)="Partial","◐","✗"))&" Spending limit"&CHAR(10)&IF(LEFT(E7,3)="Yes","✓",IF(LEFT(E7,7)="Partial","◐","✗"))&" Levy limit"&CHAR(10)&IF(LEFT(F7,3)="Yes","✓",IF(LEFT(F7,7)="Partial","◐","✗"))&" Assessment cap"&CHAR(10)&IF(LEFT(G7,3)="Yes","✓",IF(LEFT(G7,7)="Partial","◐","✗"))&" Rate cap" | D7: Yes. Taxpayer's Bill of Rights (TABOR), adopted by initiative Nov. 1992: every "district" (state, counties, cities, school districts, special districts) may grow fiscal-year spending no faster than inflation (Denver-Aurora-Lakewood CPI) plus local growth (net new construction for non-school districts; enrollment for school districts). Revenue above the limit must be refunded unless voters approve keeping it. Exempt: voter-approved revenue changes, federal funds, government-owned "enterprises" (entities receiving under 10% of revenue from state and local governments), gifts, damage awards, property sales and pension contributions. Voters may waive the limit ("de-Brucing," after TABOR author Douglas Bruce). Most counties, cities and school districts have; by 2024 only a handful of counties remained under it, and Arapahoe (71% yes) and Jefferson (57.5%) counties de-Bruced in Nov. 2024. Authority: Colo. Const. art. X §20 (TABOR, 1992). | E7: Yes. Three overlapping property tax revenue limits: 1) TABOR: a district's property tax revenue may grow no faster than inflation plus local growth, and no mill levy may rise above the prior year's without voter approval (applies unless waived). 2) 2024 statutory limit (SB24-233 as rewritten by HB24B-1001, special session Aug. 2024): property tax revenue of counties, statutory towns and special districts may grow no more than 5.25% per year of a two-year reassessment cycle (10.5% per cycle) from the highest year of the prior cycle, with carryover of unused room. Excluded from the limit: new construction, annexations and similar base growth; disaster spending; school districts; and home-rule cities and towns (including Denver, Colorado Springs and Aurora). Voters may waive it for one year, several years or permanently. 3) The older 5.5% statutory limit for non-home-rule counties, towns and special districts that have not waived it. School districts: a separate statewide limit caps total local-share school property tax revenue at 6% per year of the cycle (or base-per-pupil plus enrollment growth if higher), enforced by lowering the school residential assessment rate; only a statewide vote can waive it. Authority: Colo. Const. art. X §20(7)(c); C.R.S. 29-1-1701 to 1703; C.R.S. 29-1-301. | F7: Partial. No per-parcel cap. Values are reset every two years (as of June 30 of the prior even year), and the Legislature sets statewide assessment rates by property class, cutting them repeatedly since 2022. For 2025, residential property is assessed at 6.25% of market value for local government levies and 7.05% for school levies (lower if statewide values rose over 5%); most nonresidential classes fall from 29% to 27% (2025), 26% (2026) and 25% (2027 on). The Gallagher Amendment (1982), which fixed residential property at 45% of the statewide base, was repealed by Amendment B (2020). Authority: C.R.S. 39-1-104, 39-1-104.2 (as amended by HB24B-1001, 2024). | G7: Yes. TABOR forbids any district to levy a mill rate above the prior year's without voter approval, so every mill levy increase requires a vote. School district operating levies are also capped by statute (the lesser of the prior year's rate or 27 mills, plus voter-approved overrides). Authority: Colo. Const. art. X §20(4)(a); C.R.S. 22-54-106. | H7: Yes. School districts are under TABOR (most have de-Bruced), a statewide 2024 limit on total local-share school property tax revenue (enforced by cutting the school residential assessment rate) and the 27-mill cap on operating levies. Voter-approved mill levy overrides and bonds sit outside the formula; the state backfills school finance when the local share falls. | I7: No. TABOR prohibits any new state real property tax. All property taxes are levied locally. Authority: Colo. Const. art. X §20(8)(a). | J7: Yes. Senior homestead exemption: owners 65+ who have owned and occupied the home 10 years are taxed on only 50% of the first $200,000 of market value; the same applies to qualifying disabled veterans and Gold Star spouses. The state reimburses local governments for the lost revenue. Other homeowners get no exemption; their relief comes through the reduced residential assessment rate (and one-time value subtractions in some years). Authority: Colo. Const. art. X §3.5 (Referendum A, 2000). | K7: Yes. Property Tax, Rent and Heat Credit (PTC) rebate for low-income seniors, surviving spouses and people with disabilities, paid as a state check; plus a state property tax deferral program. Authority: C.R.S. 39-31-101 et seq. | L7: Yes. - Business personal property exemption: the state reimburses local governments each year for revenue lost when the exemption rose from $7,900 to $50,000 in 2021 (now $56,000). The FY2025-26 appropriation is $17.9 million, with $16.8 million forecast for FY2026-27; SB26-116 sets the exemption at $58,000 from 2027 and holds reimbursements at the 2026 level. - Senior and disabled veteran homestead exemption: the Constitution requires the state to reimburse local governments in full for exempting 50% of the first $200,000 of value for qualifying seniors and disabled veterans ($180.2 million in FY2025-26). Backfills for the 2022-2024 assessment-rate cuts covered only the 2023 through 2025 tax years. Higher state school aid when assessment cuts shrink the local share is school finance formula aid and does not count. Authority: Colo. Const. art. X, § 3.5; C.R.S. §§ 39-3-119.5, 39-3-207, 39-3-210; HB21-1312; HB24B-1001; SB26-116; HB26-1171. | M7: No. | N7: Partial. Governments still under TABOR or the 2024 limits must cut mill levies (often as temporary "mill levy credits") or refund revenue above the limit. De-Bruced governments can keep the prior year's mill levy while assessed values soar, which produced large unvoted increases in 2023. | O7: No. Tax increases, mill levy increases, limit waivers and debt require a simple majority of voters. | P7: Yes. TABOR tax, debt and revenue-change questions may be decided only at the state general election (November of even years), the first Tuesday in November of odd years, or a district's biennial local election (emergency taxes excepted). Authority: Colo. Const. art. X §20(3)(a). | Q7: Partial. Special districts may levy only for their statutory purposes; mill levy overrides and bonds are restricted to the purposes on the ballot. General county and city levies are unrestricted. | R7: 64 counties (two are consolidated city-counties: Denver and Broomfield); 272 municipalities; 178 school districts; more than 3,000 special districts, including more than 2,300 metropolitan districts (up from about 200 in 2000), plus fire protection, water and sanitation, park and recreation, library, hospital and cemetery districts. Census of Governments 2022: 3,715 local governments, including 3,201 special districts. | S7: Verdict: Failed. Property tax per person rose 47.2% after inflation from FY2002 to FY2024, against 25.9% for the U.S. Why it leaks: TABOR (Colo. Const. art. X, §20) caps local property tax revenue, but voters may waive it, and most local governments have de-Bruced, with Arapahoe and Jefferson counties following in Nov. 2024. The 2024 statutory limit in HB24B-1001 excludes school districts and home-rule cities such as Denver, and it lets unused room carry over. Amendment B (2020) repealed the Gallagher Amendment, which held down the residential share of the base. State backfills for assessment-rate cuts count against Colorado. How localities get around it: De-Bruced governments held mill levies flat after the 2023 reappraisal, producing large tax increases no one voted on. Developer-controlled metropolitan districts, more than 2,300 of them, levy mills on new homeowners. Full record: Colorado has had the fastest growth in homeowner property tax bills in the country: the median bill rose 45.0% after inflation from 2014 to 2024 (American Community Survey; U.S. +13.3%). The record (Census, BEA, ACS): state and local property tax was $2,379 per person in FY2024 (U.S. $2,132), 2.88% of personal income (20th-highest of 50; U.S. 2.89%). After inflation, collections per person (all state and local property tax divided by residents) rose 47.2% from FY2002 to FY2024 (U.S. +25.9%) and rose 7.8% from FY2019 to FY2024 (U.S. -1.1%). The median homeowner paid $2,828 in 2024 (U.S. $3,211); the median bill rose 36.0% after inflation from 2010 to 2024 (U.S. +9.3%). The Tax Foundation's 2026 ranking puts its effective property tax rate on owner-occupied homes at 0.50%, 7th-lowest of 50. By the same measure it was 0.58% in 2010 (U.S. 1.00% in 2010, 0.94% in 2024). Why: TABOR's statewide limit has forced refunds for decades, but locally it has been largely waived, and the 2020 repeal of the Gallagher Amendment removed the rule that held the residential share of the base down. Most local governments have de-Bruced; the remaining holdouts (Arapahoe and Jefferson counties) did so in 2024. Some de-Bruced governments kept mill levies flat as residential values jumped sharply (often 30% or more) in the 2023 reappraisal, producing large tax increases no one voted on, which drove the 2023-2024 reform fights. Workarounds: (1) Enterprises: governments fund programs through fee-financed "enterprises" exempt from TABOR (e.g., the 2009 hospital provider fee and 2021 transportation fees). (2) Metropolitan districts: developer-controlled special districts issue bonds and levy mills on new homeowners, often with board members who work for the developer; more than 2,300 exist. (3) Home-rule exemption: Denver, Colorado Springs, Aurora and other home-rule cities are exempt from the 2024 statutory limit. (4) Retained refunds: cities still under TABOR ask voters to keep revenue above the limit one purpose at a time; in May 2019 Colorado Springs officials planned to ask voters to keep up to $7 million that would otherwise have been refunded, for parks and trails (The Gazette, May 29, 2019). (5) Sales taxes: local sales tax rates average 4.99% (combined 7.89%, local rates up to 9.10%); sales taxes supply 35.3% of local taxes (U.S.: 18.5%). State response: repeated assessment-rate cuts financed partly by state backfills, which shift the cost to state taxpayers and TABOR refunds. | T7: - Common Sense Institute Iowa, "Iowa Leads the Nation in Property Tax Relief: Ranking State Reforms of the Past Decade" (Aug. 6, 2026). Ranks SB24-233 third nationally by taxpayer savings (about 0.11% of personal income, $1,401 per household over its first six years) and places HB24B-1001 in the top ten. It adds that both 2024 bills only reduced the amount by which property taxes rose after the 2020 Gallagher repeal (Amendment B), which "removed the constitutional protections that limited the growth in property taxes for homeowners." https://archive.commonsenseinstituteus.org/iowa/research/taxes-and-fees/iowa-leads-the-nation-in-property-tax-relief-ranking-state-reforms-of-the-past-decade - Independence Institute, Nash Herman, "Leviathan by Loophole: the Growth of Colorado's State Government After TABOR" (Jan. 20, 2026). Finds that inflation- and population-adjusted state spending has outgrown TABOR's intent through TABOR-exempt funds such as fee-funded enterprises. https://i2i.org/leviathan-by-loophole-the-growth-of-colorados-state-government-after-tabor/ - Independence Institute, Joshua Sharf, "Review of Colorado's Property Taxes and Model Policy" (Sept. 4, 2024). Issue Paper 3-2024 traces Gallagher, TABOR and the 2020-2024 fights and calls the statewide assessment rate "a blunt instrument for limiting property taxes" that distorts how properties are taxed. Its model caps county and city property tax revenue at last year's revenue plus inflation (that year's new construction excluded) and school district revenue at inflation plus enrollment change; voters could waive the cap, but each local board would have to pass a separate measure every year to keep the extra revenue, on the Utah Truth in Taxation model, which offers transparency and accountability. https://i2i.org/wp-content/uploads/IP_3_2024_b.pdf - Advance Colorado (taxpayer group, with Colorado Concern), Initiatives 50 and 108 and their withdrawal (Sept. 4, 2024). Initiative 50 would have written a 4% annual cap on property tax revenue growth into the constitution; Initiative 108 would have cut residential assessment rates to 5.7% and nonresidential rates to 24%, with a state backfill estimated at $3 billion. The group withdrew both after the special session passed HB24B-1001; Michael Fields said, "Today, Colorado taxpayers are the winners." https://www.denvergazette.com/2024/09/04/colorado-property-tax-ballot-initiatives-withdrawn-as-part-of-deal-with-governor-lawmakers/ - Common Sense Institute, "Reining in Property Taxes: The Voters’ Choice at the 2024 November Ballot" (Aug. 13, 2024). Full report finding that property taxes "have grown at twice the rate of population plus inflation over the past three decades" and that the statewide property tax burden rose $2.4 billion (19%) in 2023, four times faster than population plus inflation. It models Initiative 108 (average homeowner savings over $510 from 2024 to 2026) and Initiative 50 (4% statewide revenue cap) against SB24-233. https://commonsenseinstituteus.org/colorado/research/taxes-and-fees/reining-in-property-taxes-the-voters-choice-at-the-2024-november-ballot/ - Common Sense Institute, "Does SB24-233 Provide Taxpayer Relief and Predictability?" (May 8, 2024). Finds no relief: the 2024 law locks in the 27% jump in residential values from 2023, and a $400,000 home's bill rises 11% ($318) by 2026 even if its value is flat; the 5.5% cap would not prevent a repeat if values spike again, and it carves out school districts, over 50% of the tax base. https://commonsenseinstituteus.org/colorado/research/taxes-and-fees/does-sb24-233-provide-taxpayer-relief-and-predictability/ - Centennial Institute (State Policy Network associate): no property tax report since 2021 was found. - Steamboat Institute (State Policy Network associate): no property tax report since 2021 was found; it has joined a coalition to protect TABOR. https://steamboatinstitute.org/update/steamboat-institute-joins-coalition-to-protect-colorados-tabor Linked list: 7 items on the Analyses sheet (filter State = Colorado); every source URL is linked on the Sources sheet. | U7: 2020: Amendment B repealed the Gallagher Amendment (57.5% yes). 2023: Prop HH (cap local revenue growth at 6.5% in exchange for the state keeping more TABOR money) failed (about 41% yes). 2024: SB24-233 created a 5.5% local limit; to remove citizen Initiatives 50 (4% cap on property tax revenue growth) and 108 (assessment cuts) from the ballot, the August special session passed HB24B-1001 (5.25%/yr local limit, statewide school limit, rate cuts). Nov. 2024: Arapahoe and Jefferson counties de-Bruced. 2025: a referred amendment to make the senior exemption portable (HCR25-1001) died in committee. School districts came under the new statewide limit for the 2025 tax year; Legislative Council Staff set the 2026 balancing percentage (a temporary cut in the school residential assessment rate) on Feb. 5, 2026. 2026: HB26-1209 would have cut all three statutory revenue limits to 4% a year for tax years 2027-2032; the House Transportation, Housing and Local Government Committee postponed it indefinitely on March 10, 2026. Sept. 4, 2024: election officials confirmed the withdrawal of Initiatives 50 and 108 (Advance Colorado and Colorado Concern) from the 2024 ballot under the special-session deal. Nov. 3, 2026 ballot: none of the 14 certified statewide measures deals with property tax. Tax measures: Prop NN (legislative referral raising the state TABOR limit, about $500 million a year more for K-12 schools), Amendment 87 (graduated income tax on incomes over $500,000) and Prop 136 (Advance Colorado; cap income tax rates at 4.4%). | V7: 7th (0.50% effective rate; 0.58% in 2010) | W7: On paper Colorado has every tool: a constitutional spending limit with refunds, a ban on unvoted mill increases, new statutory levy limits and November-only tax elections. In practice most local governments have voted their way out of TABOR's revenue limit, home-rule cities are exempt from the 2024 levy limit, and more than 2,300 developer-run metro districts levy taxes on new homeowners. The 2023-2024 fights show that statewide initiatives (Initiative 50) can force the Legislature to act. | X7: https://leg.colorado.gov/sites/default/files/documents/2024B/bills/fn/2024b_hb24b-1001_f1.pdf https://leg.colorado.gov/sites/default/files/documents/2024B/bills/2024b_1001_rer.pdf https://leg.colorado.gov/sites/default/files/documents/2025A/bills/fn/2025a_hcr1001_00.pdf https://leg.colorado.gov/bills/HCR25-1001 https://www.coloradopolitics.com/2024/11/06/arapahoe-jefferson-county-officials-cheer-de-brucing-wins https://yellowscene.com/2023/05/18/colorado-homeowners-are-fed-up-with-metro-districts-but-reforms-are-hard-to-come-by/ https://www.lincolninst.edu/app/uploads/2024/10/revenue_and_expenditure_limits_2022.xlsx https://taxfoundation.org/research/state-tax/2026-state-tax-ballot-measures/ https://www.leg.colorado.gov/bills/sb24-233 https://leg.colorado.gov/bills/HB26-1209 https://content.leg.colorado.gov/publications/report-2026-property-tax-balancing-percentage https://kiowacountypress.net/content/14-measures-will-appear-colorados-statewide-ballot-2026 https://www.denvergazette.com/2024/09/04/colorado-property-tax-ballot-initiatives-withdrawn-as-part-of-deal-with-governor-lawmakers/ https://gazette.com/?p=1097373 https://leg.colorado.gov/sites/default/files/documents/2024A/bills/2024a_233_rev.pdf
A8: Connecticut | B8: F. Restriction points 2 of 18 (assessment cap 1; rate cap 1). Deductions: built-in loopholes -0.5; workarounds in practice +0; state buydowns +0; data record +0.5. Total 2 = F (A 11+, B 8.5-10.9, C 5.5-8.4, D 3-5.4, F under 3). Why: Built-in loopholes -0.5: the one spending limit carries broad exclusions (special education, debt service, capital) and has never been enforced. Workarounds 0: with no binding limit there is little to work around. Buydowns 0: the car-tax grant, PILOTs and the circuit breaker appear to be below 5% of the $12.57 billion FY2024 total (not computed). Record +0.5: real growth per person of 19% (FY2002-FY2022, U.S. 23.4%) and -13.3% (FY2019-FY2024, U.S. -1.1%), and real homeowner bills down 6.8% since 2010, against a heavy level (3.50% of income, 43rd; 1.66% effective rate, 48th). | C8: =((LEFT(D8,3)="Yes")+(LEFT(E8,3)="Yes")+(LEFT(F8,3)="Yes")+(LEFT(G8,3)="Yes"))&" of 4 in force"&IF(((LEFT(D8,7)="Partial")+(LEFT(E8,7)="Partial")+(LEFT(F8,7)="Partial")+(LEFT(G8,7)="Partial"))>0," + "&((LEFT(D8,7)="Partial")+(LEFT(E8,7)="Partial")+(LEFT(F8,7)="Partial")+(LEFT(G8,7)="Partial"))&" partial","")&CHAR(10)&CHAR(10)&IF(LEFT(D8,3)="Yes","✓",IF(LEFT(D8,7)="Partial","◐","✗"))&" Spending limit"&CHAR(10)&IF(LEFT(E8,3)="Yes","✓",IF(LEFT(E8,7)="Partial","◐","✗"))&" Levy limit"&CHAR(10)&IF(LEFT(F8,3)="Yes","✓",IF(LEFT(F8,7)="Partial","◐","✗"))&" Assessment cap"&CHAR(10)&IF(LEFT(G8,3)="Yes","✓",IF(LEFT(G8,7)="Partial","◐","✗"))&" Rate cap" | D8: No. (cap suspended for FY2026 and FY2027) Connecticut's only municipal spending limit, a soft cap tied to state aid, is suspended. Since FY2018, a municipality that raises adopted budget expenditures by more than 2.5% or the rate of inflation (whichever is greater) loses 50 cents of its Municipal Revenue Sharing grant for each dollar over the cap. Excluded: debt service, special education, court orders and arbitration awards, declared disasters, audited deficits, nonrecurring grants, capital items of $100,000+ and unfunded pension payments. Inflation set the FY2024 cap at 6.18%. PA 25-3 (SB 1553, 2025) barred the Office of Policy and Management from cutting grants for FY2026, and section 175 of the 2026 budget act (SB 1, signed May 26, 2026) bars enforcement in FY2026 and FY2027. The Office of Fiscal Analysis reports that, as of May 1, 2026, no violation had ever been enforced, and that the Municipal Revenue Sharing Fund had no money left at the close of FY2025 to pay the grant used to enforce the cap. Coded No: the cap has never been applied and is suspended through June 30, 2027. Authority: Conn. Gen. Stat. §4-66l(f) (PA 17-2, June Special Session 2017); PA 25-3 (2025); SB 1 (2026), §175. | E8: No. No limit on growth in municipal property tax levies. Town budgets are set by town meeting, referendum or council vote, with the mill rate set to balance the budget. | F8: Partial. No assessment growth cap. Property is assessed at 70% of market value and revalued every five years. Municipalities may phase in revaluation increases over up to five years (choosing to phase in 25%-100% of the increase), and the legislative body can end a phase-in. Authority: Conn. Gen. Stat. §12-62a (70% ratio); §12-62c (phase-in option, 1987). | G8: Partial. No cap on real property mill rates. Motor vehicles are the exception: the mill rate on cars is capped at 32.46 mills (combined with any special district or borough levy), and the state reimburses towns for revenue lost to the cap through a sales-tax-funded grant. Authority: Conn. Gen. Stat. §12-71e (as amended by PA 22-118). | H8: No. Schools are departments of towns (or regional districts that bill member towns), so school costs flow straight into the town mill rate; nothing limits their growth. Special education is excluded even from the soft spending cap. | I8: No. No state property tax. | J8: Partial. No mandatory homestead exemption. A 2024 law lets a town exempt 5% to 35% of the assessed value of a primary residence; only one municipality had adopted it by April 2026. The 2026 session (SB 1) adds a second local option: a $50,000 assessed-value homestead exemption starting with the Oct. 1, 2027 grand list (a town may not use both). Veterans and seniors have separate exemptions and local options. Authority: Conn. Gen. Stat. §12-81oo (2024); SB 1 (2026), §§224-225. | K8: Yes. Elderly/disabled homeowners circuit breaker: credit of up to $1,250 (married) or $1,000 (single) for homeowners 65+ or totally disabled with 2025 income under $56,500 (married) or $46,300 (single), applied to the tax bill. State income tax credit for property taxes on a home or car: up to $300, income-limited, now open to all adults meeting the income test. Renters' rebate for seniors and disabled renters. Local options for tax freezes and deferrals. Authority: Conn. Gen. Stat. §12-170aa; §12-704c; §12-170d. | L8: Yes. - Motor Vehicle Tax Grant: the state reimburses towns for revenue lost to the statewide 32.46-mill cap on motor vehicle property tax rates; $127.5 million in FY2026 and $111.6 million in FY2027 under the revised budget. - Tiered PILOT: the state pays towns in lieu of taxes on private colleges and hospitals that state law exempts, and on state-owned property; $346.0 million in FY2026 and $354.3 million in FY2027 for both together. Both grants are paid from the Municipal Revenue Sharing Fund, which receives a diversion of sales tax revenue and a General Fund transfer. Smaller reimbursements cover added exemptions for veterans and people with disabilities. Authority: CGS §§ 4-66l, 12-71e, 12-18b, 12-20a; OFA FY 26 and FY 27 Budget, Part V Municipal Aid; OFA FY 27 Connecticut Budget Revisions (PA 26-68). | M8: No. | N8: No. No rollback after revaluation. Towns set the mill rate to fund the budget; revaluation shifts the burden among classes and owners. | O8: No. No state supermajority requirement for local tax increases. Some town charters require referenda on budgets, decided by majority. | P8: No. Town budget referenda are held on dates set by charter, usually in spring. | Q8: No. The general town levy is unrestricted. Special taxing districts (fire, sewer and similar) levy only for their purposes. | R8: 169 towns and cities (no county government since 1960); 17 regional school districts, which bill member towns and levy no tax directly; about 430 special districts and boroughs in the Census count, including fire districts and other special taxing districts that levy their own mill rates. Census of Governments 2022: 629 local governments. | S8: Verdict: Partly. Property tax per person rose 13.2% after inflation from FY2002 to FY2024, against 25.9% for the U.S., and fell 13.3% from FY2019 to FY2024 with no binding limit in place; the FY2024 level of $3,422 per person tops the U.S. $2,132. Why it leaks: Connecticut has no levy limit. Its one mill rate cap covers cars (Conn. Gen. Stat. §12-71e). The sole spending limit, a grant penalty under §4-66l(f), has never been enforced and is suspended for FY2026 and FY2027 by SB 1. Towns receive sales-tax-funded state grants with no duty to cut rates, a subsidy that counts against the state. How localities get around it: There is little to work around. Bridgeport cut its FY2027 mill rate about 40% after revaluation, and with no rollback rule that cut does not show whether its levy fell. Full record: Has it worked? There is little to work around. Connecticut has no levy limit and no rate cap on homes, and its only spending limit is a grant penalty that, by the Legislature's own fiscal office, had never been enforced as of May 2026 and is suspended for FY2026 and FY2027; inflation allowed 6.18% growth in FY2024. Property tax is nearly the only local tax (98.5% of local tax revenue, Census FY2022). The record (Census, BEA, ACS): state and local property tax was $3,422 per person in FY2024 (U.S. $2,132), 3.50% of personal income (8th-highest of 50; U.S. 2.89%). After inflation, collections per person (all state and local property tax divided by residents) rose 13.2% from FY2002 to FY2024 (U.S. +25.9%) and fell 13.3% from FY2019 to FY2024 (U.S. -1.1%). The median homeowner paid $6,573 in 2024 (U.S. $3,211); the median bill fell 6.8% after inflation from 2010 to 2024 (U.S. +9.3%). The Tax Foundation's 2026 ranking puts its effective property tax rate on owner-occupied homes at 1.54%, 48th-lowest of 50. By the same measure it was 1.38% in 2010 (U.S. 1.00% in 2010, 0.94% in 2024). Where caps exist, the state pays for them: the motor vehicle mill rate cap is funded by diverting state sales tax to towns. The 2026 budget deal added municipal aid pitched as property tax relief, with no requirement that towns cut rates: about $270 million by the Yankee Institute's count, and a $272.9 million increase including $100 million in one-time aid by the Governor's office. Revaluation: towns may phase in increases, and the 2026 session let Hartford delay its Oct. 1, 2026 revaluation by a year. Bridgeport cut its FY2027 mill rate about 40%, to 27.95, after revaluation raised its grand list to about $13 billion; with no rollback or truth-in-taxation rule, the lower rate alone does not show whether the city's levy fell (City of Bridgeport, May 20, 2026). Big cities: the FY2027 state budget raised state funding for Hartford by $33.6 million, Bridgeport by $25.4 million and New Haven by $20.1 million, part of a $272.9 million statewide increase that includes $100 million in one-time municipal aid (Office of the Governor, May 3, 2026). The state carries the cost while city budgets stay outside any binding limit. | T8: - Yankee Institute, Meghan Portfolio, "When Connecticut Mandates, Towns Pay" (Aug. 21, 2026). A review of the state's 2020-2025 mandate reports found at least 104 public and special act entries that leave towns or school districts with some of the cost of compliance; 58 had no dollar cost assigned by the Office of Fiscal Analysis, and 28 involved schools. Backs Rep. Mitch Bolinsky's bill, filed in 2023 and 2025 without a hearing, to require a two-thirds vote in both chambers to create or expand an unfunded mandate, and notes that Maine requires the state to cover 90 percent of the added local cost of a mandate. https://www.yankeeinstitute.org/2026/08/21/when-connecticut-mandates-towns-pay/ - Yankee Institute, Meghan Portfolio, "A Task Force, Numerous Bills and a Car Tax That Refuses to Die" (July 24, 2026). Towns collect about $1 billion a year in motor vehicle property tax, and repeated bills to phase it out with state reimbursement have gone nowhere. The task force co-chaired by Sen. MD Rahman (D-Manchester) recommended letting towns drop the tax and tax a larger share of the value of homes and businesses, which Yankee calls "a tax shift." https://www.yankeeinstitute.org/2026/07/24/a-task-force-numerous-bills-and-a-car-tax-that-refuses-to-die/ - Yankee Institute, Meghan Portfolio, "Connecticut’s “Relief” for Towns Needs Safeguards — Or It Risks Becoming the Next Tax Increase" (April 29, 2026). The proposed $270 million in new municipal aid carries no requirement to cut or stabilize taxes, and one-time money tends to become permanent spending. It asks that the funds be limited to closing deficits and preventing mill rate increases, with towns disclosing what their tax rate would have been without the aid. Towns that do not need the money should pass it to taxpayers through lower tax rates or other local relief. https://www.yankeeinstitute.org/2026/04/29/connecticuts-relief-for-towns-needs-safeguards-or-it-risks-becoming-the-next-tax-increase/ - Yankee Institute, Meghan Portfolio, "Connecticut Does it Again: Still Top Three in Property Taxes" (March 19, 2026). Uses the Tax Foundation's Census-based ranking: Connecticut has the third-highest effective property tax rate (about 1.54 percent, against New York's 1.30 percent) for the third year running, after ranking fifth a few years earlier, trailing only New Jersey and Illinois. https://www.yankeeinstitute.org/2026/03/19/connecticut-does-it-again-still-top-three-in-property-taxes/ - Yankee Institute, Meghan Portfolio, "Progressives Push Trio of ‘Tax-the-Rich’ Bills — Including New State Property Tax" (Feb. 26, 2026). Criticizes Senate Bill 101, the first state-level property tax Connecticut would impose, at 2 to 4 mills on homes assessed above $3 million, heard alongside income tax and capital gains surcharges. https://www.yankeeinstitute.org/2026/02/26/progressives-push-trio-of-tax-the-richm-bills-including-new-state-property-tax/ - Connecticut Senate Republicans (reported by the Connecticut Business and Industry Association), "Senate GOP Releases $1.5B Tax, Energy Relief Plan" (Feb. 12, 2026). Would cut income tax rates and give individuals earning under $100,000 and couples under $200,000 a fully refundable state income tax credit for motor vehicle taxes paid to towns (estimated under $600 million a year), keeping the $300 property tax credit. https://www.cbia.com/?p=174685 - Reason Foundation, Mariana Trujillo and Bryce Chinault, "Connecticut’s fiscal guardrails are a solution, not the problem" (Dec. 10, 2024). Answers the Connecticut Conference of Municipalities, which blamed rising property taxes on the 2017 guardrails that cap state spending growth and send surpluses to pension debt. Pension costs rose from 6.5% of payroll in 1995 to 39% in 2024, two-thirds of it for past debt, and $7.7 billion in extra contributions from FY2020 to FY2023 freed about $738 million a year in the state budget; it tells towns that want more education aid or tax relief to back the guardrails. https://reason.org/commentary/connecticuts-fiscal-guardrails-are-a-solution-not-the-problem/ Linked list: 7 items on the Analyses sheet (filter State = Connecticut); every source URL is linked on the Sources sheet. | U8: 2017: municipal spending cap created (grant penalty). 2022: car tax cap lowered to 32.46 mills (PA 22-118). 2024: local-option homestead exemption (5%-35% of assessed value) enacted; one town adopted it. 2025: PA 25-3 (SB 1553) suspended enforcement of the municipal spending cap for FY2026. 2026: SB 1 adds a local-option $50,000 homestead exemption from Oct. 1, 2027; SB 477 allows Hartford to delay revaluation; the budget deal added a one-time $270 million in municipal aid; section 175 of the budget act (SB 1, signed May 26, 2026) bars spending-cap enforcement in FY2026 and FY2027. Senate Republicans proposed a refundable income tax credit for car taxes (Feb. 10, 2026); the car tax remains. A proposed statewide property tax on high-value homes was heard by the Finance, Revenue and Bonding Committee on Feb. 27, 2026 and was not enacted. No statewide property tax measure on the Nov. 2026 ballot. | V8: 48th (1.54% effective rate; 1.38% in 2010) | W8: Connecticut has none of the four regimes in binding form: no levy limit, no assessment cap, a rate cap only on cars, and a municipal spending cap enforced through a grant penalty that has never been applied and is suspended through FY2027. Property taxes fund almost all local government, and the state's response has been grants and local-option exemptions. | X8: https://portal.ct.gov/-/media/opm/igpp/munfinsr/ucoa/ceo-cfo-spending-cap-letter-fy24.pdf https://prdext3.cga.ct.gov/2025/FN/PDF/2025SB-01553-R00-FN.PDF https://prdext3.cga.ct.gov/2022/rpt/pdf/2022-R-0217.pdf https://www.pullcom.com/for-what-it-may-be-worth/connecticuts-2026-legislative-session-yields-property-tax-changes https://www.pullcom.com/for-what-it-may-be-worth/homestead-property-tax-exemption-bill-advances-in-connecticut https://my.aarpfoundation.org/property-taxes/taxpayer-states/connecticut/ https://www.cga.ct.gov/current/pub/chap_203.htm https://www.lincolninst.edu/app/uploads/2024/12/assessment_limits_2022-3.xlsx https://www.wshu.org/connecticut-news/2026-04-29/ct-budget-aid-increase-cities-towns https://prdext3.cga.ct.gov/2025/sum/pdf/2025SUM00003-R01SB-01553-SUM.pdf https://prdext3.cga.ct.gov/2026/FN/PDF/2026SB-00001-R01-FN.PDF https://www.wtnh.com/news/connecticut/lamont-signs-fy-2027-state-budget-adjustment-bill-into-law/amp/ https://portal.ct.gov/governor/news/press-releases/2026/05-2026/governor-lamont-announces-town-by-town-increase-in-state-funding https://www.bridgeportct.gov/news/mayor-ganim-announces-lowest-mill-rate-decades-city-council-approves-historic-40-mill-rate-reduction https://www.cbia.com/?p=174685
A9: Delaware | B9: D. Restriction points 6.25 of 18 (levy limit 2; rate cap 1; truth in taxation 2; rollback 0.5; school districts covered 0.5; use restrictions 0.25). Deductions: built-in loopholes -2; workarounds in practice -1; state buydowns +0; data record +0.5. Total 3.75 = D (A 11+, B 8.5-10.9, C 5.5-8.4, D 3-5.4, F under 3). Why: Built-in loopholes -2: the limits apply only in reassessment years; counties may take 15% more revenue and school boards took up to 10% more in 2025 without a vote; match and tuition taxes need no referendum, and from FY2031 boards may raise rates 2% a year without one. Workarounds -1: New Castle County proposed a 17.2% county tax increase for FY2027 a year after reassessment, and the Legislature let school districts shift taxes onto businesses with split rates (now 1.85x). Buydowns 0: the Senior School Property Tax Credit is far below 5% of the $1.14 billion FY2024 total. Record +0.5: a low level (1.66% of income, 5th lowest; 0.47% effective rate) and slow homeowner bill growth (1.5% real since 2010), offset by fast long-run growth per person (43.1%, FY2002-FY2022, U.S. 23.4%); the data end before the 2025 reassessment bills. | C9: =((LEFT(D9,3)="Yes")+(LEFT(E9,3)="Yes")+(LEFT(F9,3)="Yes")+(LEFT(G9,3)="Yes"))&" of 4 in force"&IF(((LEFT(D9,7)="Partial")+(LEFT(E9,7)="Partial")+(LEFT(F9,7)="Partial")+(LEFT(G9,7)="Partial"))>0," + "&((LEFT(D9,7)="Partial")+(LEFT(E9,7)="Partial")+(LEFT(F9,7)="Partial")+(LEFT(G9,7)="Partial"))&" partial","")&CHAR(10)&CHAR(10)&IF(LEFT(D9,3)="Yes","✓",IF(LEFT(D9,7)="Partial","◐","✗"))&" Spending limit"&CHAR(10)&IF(LEFT(E9,3)="Yes","✓",IF(LEFT(E9,7)="Partial","◐","✗"))&" Levy limit"&CHAR(10)&IF(LEFT(F9,3)="Yes","✓",IF(LEFT(F9,7)="Partial","◐","✗"))&" Assessment cap"&CHAR(10)&IF(LEFT(G9,3)="Yes","✓",IF(LEFT(G9,7)="Partial","◐","✗"))&" Rate cap" | D9: No. No cap on county, municipal or school district spending growth. School districts' local operating revenue is restrained only by the referendum requirement for tax rate increases (see Rate limits); no spending formula applies. | E9: Partial. Reassessment-year limits only. Counties: after a total reassessment the county must compute a "rolled-back rate" that raises the same revenue as the prior year, but may adopt a rate yielding up to 15% more revenue in the first year (new construction excluded from the calculation). School districts: for reassessments before Jan. 1, 2026, a board could set a rate raising up to 10% more operating revenue without a referendum (a 1972 provision unused for decades because counties never reassessed; in 2025 boards took from 1% to the full 10%). For later reassessments the cap is prior-year operating revenue plus the district's five-year average growth rate in taxable property. Outside reassessment years there is no levy limit. Authority: 9 Del. C. §8002(c)-(e); 14 Del. C. §1916(b) (as amended 2025-2026). | F9: No. No annual assessment cap. Counties went decades without reassessing (base years 1974 in Sussex and 1980s in Kent and New Castle) until a 2020 Chancery Court ruling that the stale values violated the Constitution's uniformity clause; the settlement forced countywide reassessments in 2021-2025. HB 62 (2023) now requires reassessment every five years. Average New Castle County residential assessments rose about 433% when values were updated. Authority: Del. Code tit. 9 ch. 83; HB 62 (2023). | G9: Partial. No overall rate cap. School districts need a referendum (majority vote) to raise the current-expense tax rate, but boards may levy some taxes without one: the local share needed to match state appropriations (§1902(b)) and the tuition tax for students sent to other districts (§602(e)). A 2026 change also lets a board raise its rate up to 2% a year without a referendum (if reserves are under 10% of revenue), starting in FY2031 or after the district's next post-reassessment reset. County and municipal councils set rates by ordinance. Authority: 14 Del. C. §§602(e), 1902(b), 1903, 1914(b), 1916. | H9: Partial. Schools are covered by the referendum requirement for operating rates, but match and tuition taxes (and, in the 2021-2025 reassessments, a 10% post-reassessment allowance) let boards raise revenue without a vote. Since 2025, New Castle County school districts may set split rates (non-residential up to 2x residential under HB 242; 1.85x under HB 462, which became law without the governor's signature in August 2026). | I9: No. No state property tax. The state funds about 60% of school costs through its unit-based formula; local school property taxes provide about 31%. | J9: Partial. No general homestead exemption. Counties grant elderly and disabled exemptions (New Castle County raised its value limit from $32,000 to $173,000 and income limits to $50,000 single / $65,000 couple after reassessment; HB 159 of 2025 allowed the school-tax elderly exemption to be updated too). Authority: 14 Del. C. §1902 (exemption amounts updated after reassessment); HB 159 (2025). | K9: Yes. Senior School Property Tax Credit: the state pays 50% of a senior homeowner's school property tax (non-debt portion), up to $500, for eligible owners 65+. HB 241 (2025) requires counties to offer installment plans when a primary-residence school tax bill rises $300 or more. Authority: Delaware Senior School Property Tax Credit program (Department of Finance). | L9: Partial. The state pays half of the regular school property tax on the primary residence of homeowners 65 and older, up to $500 a year, as a credit on the school tax bill; people who moved to Delaware in 2018 or later must have lived in the state 10 years. A separate state fund pays a school tax credit for eligible veterans. The FY2027 budget appropriates $33.0 million to the Elder Tax Relief and Education Expense Fund and $3.5 million to the Veterans Tax Relief Education Expense Fund. State school funding through the unit formula is general school aid and does not count. Authority: 14 Del. C. § 1917; SB 335 (FY2027 Appropriations Act), § 1 (OMB 10-02-11) and § 69. | M9: Yes. After a total reassessment, the county ordinance setting the tax rate must state the percentage by which the rate exceeds the rolled-back rate, and the county must advertise that percentage increase in a newspaper within 15 days. Delaware is the only truth-in-taxation state that requires no public hearing on the levy. Coded Yes because Delaware meets two of the three key truth-in-taxation requirements (a rollback rate calculation, mailed parcel-specific notices and a governing-body vote to exceed the rollback rate). Authority: 9 Del. C. §8002(e). | N9: Partial. Rollback is required only in reassessment years, and it is soft: counties may still capture up to 15% more revenue, and school districts could take up to 10% more in the 2021-2025 reassessments (future reassessments: five-year average base growth) without a vote. | O9: No. School tax referenda pass by simple majority; councils set county and municipal rates by ordinary vote. | P9: No. School referenda are scheduled by each district, often in winter or spring. | Q9: Partial. School taxes are split into current-expense, debt service, tuition and match levies, each restricted to its purpose. County and municipal general levies are unrestricted. | R9: 3 counties; 57 municipalities; 19 school districts (16 regular and 3 vocational-technical); tax ditch and other special districts (233 drainage districts in the Census count). Census of Governments 2022: 334 local governments. | S9: Verdict: Partly. Property tax per person rose 25.6% after inflation from FY2002 to FY2024, just under the U.S. 25.9%, and fell 7.2% from FY2019 to FY2024, a record that predates the 2025 reassessment bills. Why it leaks: Delaware's levy limits apply only in reassessment years, when counties may take 15% more revenue in the first year (9 Del. C. §8002); between reassessments no levy limit or rollback applies. Delaware has no spending limit and no assessment cap. School boards levy match taxes (§1902(b)) and tuition taxes (§602(e)) without a referendum. How localities get around it: After the 2025 reassessment, many school boards took up to 10% more revenue with no referendum. One year later, New Castle County Executive Marcus Henry proposed a 17.2% county tax increase for FY2027. Full record: Has it worked? Through FY2024 the tax stayed low, mostly because counties did not reassess for decades; the 2025 reassessment bills fall after the data used here. The record (Census, BEA, ACS): state and local property tax was $1,086 per person in FY2024 (U.S. $2,132), 1.66% of personal income (46th-highest of 50; U.S. 2.89%). After inflation, collections per person (all state and local property tax divided by residents) rose 25.6% from FY2002 to FY2024 (U.S. +25.9%) and fell 7.2% from FY2019 to FY2024 (U.S. -1.1%). The median homeowner paid $1,750 in 2024 (U.S. $3,211); the median bill rose 1.5% after inflation from 2010 to 2024 (U.S. +9.3%). The Tax Foundation's 2026 ranking puts its effective property tax rate on owner-occupied homes at 0.54%, 12th-lowest of 50. By the same measure it was 0.44% in 2010 (U.S. 1.00% in 2010, 0.94% in 2024). Delaware avoided property tax increases for decades by never reassessing, which a court declared unconstitutional in 2020. Once values were updated, the law's built-in windfalls kicked in: counties may take 15% more revenue in the first year, and school boards could take up to 10% without a referendum; many boards took some or all of the 10% in 2025, citing federal funding cuts and salary costs. The Legislature has since replaced the 10% allowance with a five-year-average growth limit for future reassessments. Referendum workarounds: school boards levy match taxes (§1902(b)) and tuition taxes (§602(e)) without voter approval, and from FY2031 may raise operating rates 2% a year without a vote (§1914(b), added 2026). Shift onto homeowners: the reassessment moved burden from commercial property to homes in New Castle County; the Legislature chose to let districts tax businesses up to 2x (now 1.85x) the residential rate. Big counties: one year after reassessment, New Castle County Executive Marcus Henry proposed a 17.2% increase in the county property tax for FY2027 ($102 for the median household) to close a $42 million structural deficit; outside reassessment years no levy limit or rollback applies, and Wilmington City Council urged the county council to reject the increase (Resolution 0224, April 16, 2026; Town Square Delaware). Rate resets: HB 461 (2026) lets school districts reset tax rates again as appeals and quality-control reviews change the New Castle County roll, with tax warrants due by Oct. 22, 2026 (Delaware Public Media, June 30, 2026). Overall burden: Delaware has no sales tax and low property taxes (effective rate about 0.54%); property tax is 79.6% of local tax revenue (Census FY2022). | T9: - Delaware House Republicans, "Contentious Two-Tier Tax Bill Becomes Law Without the Governor's Signature" (Aug. 7, 2026). Reports that HB 462 lets New Castle County school districts tax non-residential property at 1.85 times the residential rate, extending a temporary fix for reassessment bills that rose faster for homes than for commercial property. Gov. Matt Meyer let it become law while objecting that apartments, assessed as commercial, push the higher rate onto renters. https://housegop.delaware.gov/2026/08/07/delaware-two-tier-school-tax-bill/ - Caesar Rodney Institute, "SB 322: Delaware Should Not Put School Property Taxes on Autopilot" (June 12, 2026). Opposes SB 322, which swaps the 10% post-reassessment cap for a formula and lets districts raise school taxes up to 2% a year without a referendum when operating reserves stay under 10% of revenue; a 2% annual rise compounds to 21.9% over 10 years, lifting a $3,023 school bill on a $378,000 Christina home to about $3,685. Notes district enrollment grew 0.38% from 2015 to 2025 and asks for State Auditor efficiency audits and outcome reporting before any automatic taxing authority. https://www.caesarrodney.org/post/sb-322-delaware-should-not-put-school-property-taxes-on-autopilot - Delaware House Republicans, "The Road to Equity: Delaware's Property Reassessment Crisis" (Feb. 27, 2026). Notes the local property tax share supplies about 29% of school revenue (state about 53%) and 81% of a New Castle County property tax bill. Argues the court-ordered reassessment left school funding inequities in place, with taxes still rising in lower-income districts. https://housegop.delaware.gov/2026/02/27/delaware-property-reassessment-equity/ - Delaware House Republicans, "Legislative Probe into Property Reassessment Process Begins" (Oct. 4, 2025). Covers the first special committee hearing, where County Executive Marcus Henry said then-County Executive Matt Meyer held tentative value notices until after the November 2024 election, and Tyler Technologies reported inconsistencies in 55% of 11,500 informal appeals. Rep. Kevin Hensley also faulted the vendor for valuing preserved farmland the same as farmland with development rights. https://housegop.delaware.gov/2025/10/04/legislative-property-reassessment-investigation/ - Caesar Rodney Institute, Charlie Copeland, "Delaware Policy Choices Caused the Property Tax Problem" (Sept. 24, 2025). Argues New Castle County's reassessment, its first since the early 1980s, shifted roughly 10 percentage points of the tax base from commercial to residential property because the county economy stagnated, with real GDP growth of 0.34% a year from 2001 to 2023 against 2.03% nationally, a decline it ties partly to the 1997 Unified Development Code. Calls for regular reassessments and permitting reform beyond "Ready in 6." https://www.caesarrodney.org/post/delaware-policy-choices-caused-the-property-tax-problem - Delaware House Republicans, Joseph Fulgham, "Legislative Democrats to Continue Self-Serving Work to Clean Up NCCo's Reassessment Snafu" (Aug. 29, 2025). Says New Castle County residential values rose more than fivefold since 1983 while commercial values lagged, shifting the burden to homeowners. Faults Democrats for rushing special-session bills while ignoring Republican bills to double the senior property tax credit (HB 73) and to limit reassessment school tax hikes (HB 245 and HB 246). https://housegop.delaware.gov/2025/08/29/ncco-reassessment-political-fix/ - Delaware House and Senate Republican caucuses, "House & Senate Republicans Propose Bills, Urge Special Session to Deal with Reassessment Aftermath" (July 25, 2025). Blames the school-district allowance to raise total revenue up to 10% after reassessment (14 Del. C. §1916), which the Appoquinimink board used on July 8, 2025, for turning a revenue-neutral reset into a tax increase. Backs Rep. Mike Smith's bill limiting such increases to districts facing a projected deficit, retroactive to July 1, 2025. https://housegop.delaware.gov/2025/07/25/house-senate-republicans-propose-bills-urge-special-session-to-deal-with-reassessment-aftermath/ Linked list: 8 items on the Analyses sheet (filter State = Delaware); every source URL is linked on the Sources sheet. | U9: 2020: Chancery Court ruled Delaware's assessment system unconstitutional; settlement required reassessments in all three counties. 2023: HB 62 requires reassessment every five years. Aug. 2025 special session (after New Castle County bills spiked): HB 242 (split school rates in New Castle County, non-residential up to 2x), SB 203/SB 204 (municipal and county split-rate authority), HB 240 (refunds after appeals), HB 241 (payment plans), SCR 122 (review of the reassessment). 2026: SB 228 (quality-control review of non-residential parcels, enacted Feb. 2026); amendments to 14 Del. C. §§1914 and 1916 replaced the 10% reassessment windfall with a five-year-average growth limit and authorized 2% annual school rate increases without referendum (from FY2031); the General Assembly passed HB 460-463 by June 30, 2026 (split rates made permanent at 1.85x, rate resets capped at projected revenue, senior school exemption parity) and a Property Tax Relief and Modernization Working Group to study homestead exemptions, circuit breakers and assessment caps. HB 462, the permanent split school rate for New Castle County, became law without Gov. Meyer's signature in August 2026. | V9: 12th (0.54% effective rate; 0.44% in 2010) | W9: Delaware has almost no limitation regime: no spending cap, no assessment cap, no general rate cap, and levy rules that apply only in reassessment years (counties may still take a 15% windfall). School referenda are the main check, and boards can sidestep them with tuition and match taxes. The 2025 reassessment shock has opened a debate over homestead exemptions and assessment caps. | X9: https://www.newarkpostonline.com/news/bill-bans-school-property-tax-increases-from-reassessments/article_d90d5490-8380-5fb8-b6fd-71fbb67a9008.html https://www.delawarepublic.org/politics-government/2025-08-08/what-changes-are-on-the-table-for-tax-relief-following-reassessment-turmoil https://www.nfib.com/news/news/delaware-2025-special-session-what-you-need-to-know/ https://housedems.delaware.gov/2026/06/19/house-addresses-issues-in-statewide-property-reassessment-process/ https://delcode.delaware.gov/title14/c019/index.html https://www.lincolninst.edu/app/uploads/2024/10/truth_in_taxation_2024.xlsx https://www.lincolninst.edu/app/uploads/2025/01/levy_limits_2022.xlsx https://housegop.delaware.gov/2026/08/07/delaware-two-tier-school-tax-bill/ https://delawarelive.com/delaware-lawmakers-advance-new-castle-county-property-tax-reassessment-reforms-as-debate-shifts-to-long-term-tax-policy/ https://housegop.delaware.gov/2026/02/27/delaware-property-reassessment-equity/ https://www.delawarepublic.org/politics-government/2026-06-30/final-day-of-delawares-153rd-legislative-session https://www.wilmingtoncitycouncil.com/wp-content/uploads/2026/04/0224-A-Resolution-Urging-the-New-Castle-County-Council-to-Oppose-the-Proposed-17.2-Tax-Increase-for-FY2027-cj.pdf https://townsquaredelaware.com/tag/new-castle-county-budget/
A10: Florida | B10: B. Restriction points 13.25 of 18 (levy limit 4; assessment cap 2; rate cap 2; truth in taxation 2; rollback 1; supermajority 1; school districts covered 0.5; November-ballot rule 0.5; use restrictions 0.25). Deductions: built-in loopholes -2; workarounds in practice -1.5; state buydowns +0; data record -0.5. Total 9.25 = B (A 11+, B 8.5-10.9, C 5.5-8.4, D 3-5.4, F under 3). Why: Built-in loopholes -2: governing bodies may exceed the rollback ceiling by a 2/3 vote (up to 110%) or a unanimous or 3/4 vote, a rate adopted above the limit becomes the new base, and school levies, voted millage and non-ad valorem assessments sit outside the levy limit. Workarounds -1.5: in 2025, 58 of 67 counties adopted rates above rollback and local operating levies rose 7.9% ($1.44 billion above rollback); fees are 44% of local own-source revenue and CDD assessments ride on new subdivisions. Buydowns 0: no state program pays local governments to cut rates. Record -0.5: slow long-run growth per person (7.9% real, FY2002-FY2022, U.S. 23.4%) offset by fast recent growth (13.5%, FY2019-FY2024, U.S. -1.1%, 48th) and homeowner bill growth of 16.2% real since 2010 (U.S. 9.3%). | C10: =((LEFT(D10,3)="Yes")+(LEFT(E10,3)="Yes")+(LEFT(F10,3)="Yes")+(LEFT(G10,3)="Yes"))&" of 4 in force"&IF(((LEFT(D10,7)="Partial")+(LEFT(E10,7)="Partial")+(LEFT(F10,7)="Partial")+(LEFT(G10,7)="Partial"))>0," + "&((LEFT(D10,7)="Partial")+(LEFT(E10,7)="Partial")+(LEFT(F10,7)="Partial")+(LEFT(G10,7)="Partial"))&" partial","")&CHAR(10)&CHAR(10)&IF(LEFT(D10,3)="Yes","✓",IF(LEFT(D10,7)="Partial","◐","✗"))&" Spending limit"&CHAR(10)&IF(LEFT(E10,3)="Yes","✓",IF(LEFT(E10,7)="Partial","◐","✗"))&" Levy limit"&CHAR(10)&IF(LEFT(F10,3)="Yes","✓",IF(LEFT(F10,7)="Partial","◐","✗"))&" Assessment cap"&CHAR(10)&IF(LEFT(G10,3)="Yes","✓",IF(LEFT(G10,7)="Partial","◐","✗"))&" Rate cap" | D10: No. No cap on local government spending growth. (Florida's constitutional revenue limit binds state government only.) Local budgets are constrained through the millage rules described under Levy and Rate limits. | E10: Yes. Statutory "maximum millage" limit (2007, HB 1B): each year the most a county, city, municipal service taxing unit or independent special district may levy by majority vote is its rolled-back rate (the rate that raises last year's revenue from existing property). Until June 2026 that ceiling rose with growth in Florida per capita personal income; SB 4-F (2026 special session, signed June 24, 2026 and effective immediately) removed the adjustment. A higher rate requires a 2/3 vote of the governing body (up to 110% of the rolled-back rate), a unanimous vote or 3/4 vote of a board with nine or more members (above 110%), or a referendum. A rate adopted above the limit becomes the base going forward. Counties and cities may exceed the limit for one levy if total county or municipal taxes stay under the combined maximum. Excluded: voted millage (debt and referendum levies); school districts, which are governed by state-set school millage instead. Authority: Fla. Stat. §200.065(5); §200.185; SB 4-F (2026). | F10: Yes. Save Our Homes: the assessed value of a homestead may rise no more than 3% or the change in CPI, whichever is lower; it resets to market value on sale, but up to $500,000 of accumulated savings is "portable" to a new homestead purchased within three years. A "recapture" rule raises capped values toward market even when market values fall. Non-homestead property (rentals, second homes, commercial): increases capped at 10% a year for non-school levies; school taxes use full just value. Exclusions: new construction and improvements are added at market value (repairs after disasters excepted); change of ownership or control resets value. Authority: Fla. Const. art. VII §4(d) (Save Our Homes, approved 1992, effective 1995) and §4(g)-(h) (Amendment 1, 2008; made permanent by Amendment 2, 2018); Fla. Stat. §193.155. | G10: Yes. Constitutional caps of 10 mills each for county, municipal and school district operating taxes; a county providing municipal services may levy up to 10 more mills in unincorporated areas; special districts as set by law. Voters may approve millage above 10 mills for up to two years, or for debt. Schools: the state sets the Required Local Effort rate; boards may add up to 0.748 mill (discretionary operations as set in the appropriations act), 1.5 mills for capital outlay, and voter-approved operating millage for up to four years within the 10-mill cap. Authority: Fla. Const. art. VII §9(b); Fla. Stat. §1011.71. | H10: Partial. School districts are outside the maximum-millage levy limit and the 10% non-homestead cap (school taxes are figured on full just value for non-homestead property), but are bound by Save Our Homes, the 10-mill constitutional cap and state-set millage: the Legislature fixes the Required Local Effort rate each year, and the 2026 Amendment 3 would leave school levies untouched. | I10: Partial. The Constitution bars any state ad valorem tax on real estate or tangible personal property. The Legislature does set the Required Local Effort school millage that every district must levy to receive state formula funds, so it works as a uniform state-set school levy collected locally. Authority: Fla. Const. art. VII §1(a); Fla. Stat. §1011.62, 1011.71(1). | J10: Yes. $25,000 of a homestead's assessed value is exempt from all taxes, and a second $25,000 (on value between $50,000 and $75,000) is exempt from non-school taxes; since 2025 the second exemption is indexed to inflation (Amendment 5, 2024). Local options: an additional exemption of up to $50,000 for low-income seniors, and a full exemption for long-time low-income seniors; statewide exemptions for disabled veterans, first responders and others. Nov. 2026 Amendment 3 would raise the non-school homestead exemption to $150,000 (2027) and $250,000 (2028, indexed from 2029) and let the Legislature set a procedure for local governments to exempt homesteads entirely. Authority: Fla. Const. art. VII §6; Fla. Stat. §196.031. | K10: No. No circuit breaker or state rebate. Relief is delivered through exemptions, Save Our Homes and portability. | L10: Partial. The state appropriates money each year to the 29 fiscally constrained counties to offset ad valorem revenue lost to constitutional exemptions and assessment limits, including the additional $25,000 homestead exemption, the $25,000 tangible personal property exemption, the 10% cap on nonhomestead assessments, conservation land exemptions and the 2024 inflation adjustment to the homestead exemption. The 2026-27 budget provides about $75.2 million for these offsets. Local governments in the other 38 counties receive no reimbursement. The FEFP, including the Required Local Effort set by the Legislature, is general school aid and does not count. Authority: ss. 218.12, 218.125, 218.136 and 218.67, F.S. (reenacted in part by ch. 2026-240, Laws of Fla.); EDR, Property Taxes: Fiscally Constrained Counties (Sept. 2025). | M10: Yes. Truth in Millage (TRIM), in place since 1980: the property appraiser mails every owner a parcel-specific notice showing taxes at last year's rate, at the rolled-back rate and at each taxing authority's proposed rate, with hearing dates. Each authority must hold two public hearings (the first item discussed must be the percent increase over the rolled-back rate), and advertise a quarter-page "Notice of Proposed Tax Increase" if its rate exceeds the rolled-back rate. Exceeding the maximum millage requires the supermajorities described under Levy limit. Results: in 2025, 58 of 67 counties adopted operating millage above the rolled-back rate; statewide, local operating levies rose 7.9% over 2024 and came in $1.44 billion (4.9%) above what rolled-back rates would have raised (Florida Dept. of Revenue). Authority: Fla. Stat. §§200.065, 200.069. | N10: Yes. The rolled-back rate is computed every year and is the default ceiling for majority-vote adoption (with no adjustment for per capita income growth since SB 4-F, June 24, 2026); exceeding it triggers TRIM advertising and supermajority votes. Local governments still exceed it routinely (see TnT). | O10: Yes. Governing body: 2/3 vote to set millage up to 110% of the rolled-back rate (SB 4-F, 2026); unanimous vote (or 3/4 of boards with nine or more members) above 110%, or a referendum; unanimous or 3/4 vote to impose a new dependent district or MSTU levy. Voters: majority for voted millage. State level: 2/3 of each house to impose or raise state taxes or fees (Amendment 5, 2018). Authority: Fla. Stat. §200.065(5); Fla. Const. art. VII §19. | P10: Yes. Most local tax referenda must be held at the November general election in even-numbered years. School millage referenda: "A referendum under this part shall be held only at a general election." County millage increases above the 10-mill limit: approval by majority vote "in a general election." Every local discretionary sales surtax (adoption, amendment or renewal) must also go to a general election. Florida law defines "general election" as the first Tuesday after the first Monday in November of even-numbered years. Not covered by these sections: municipal voted levies above the 10-mill municipal cap (Fla. Stat. §200.081 sets no election date). Authority: Fla. Stat. §1011.73(3); §200.091; §212.055(10); §97.021(17). | Q10: Partial. Today the general levy is unrestricted, though municipal service taxing units, special districts and voted millage are tied to their purposes and school capital millage (1.5 mills) is restricted to capital uses. Amendment 3 (Nov. 2026) would require local governments to spend remaining property tax revenue only on "core" services: public safety, education and schools, infrastructure and natural resources. | R10: 66 counties (plus consolidated Jacksonville-Duval); 412 municipalities; 67 county school districts; independent special districts with taxing power (water management districts, hospital districts, children's services councils, fire districts, mosquito control, library and others); dependent districts and municipal service taxing units; and hundreds of developer-created community development districts (CDDs), which levy non-ad valorem assessments. Census of Governments 2022: 1,947 local governments, including 1,374 special districts. | S10: Verdict: Partly. Property tax per person rose 21.4% after inflation from FY2002 to FY2024, against 25.9% for the U.S., and grew 13.5% from FY2019 to FY2024 while the U.S. figure fell 1.1%. Why it leaks: The maximum millage limit (Fla. Stat. §200.065(5)) lets a 2/3 vote of the governing board set rates up to 110% of the rolled-back rate, and any rate adopted above the limit becomes the new base. Until SB 4-F in June 2026, the ceiling also rose with per capita personal income. School districts and voted millage sit outside the limit. Non-ad valorem assessments for fire and stormwater escape millage caps and TRIM. How localities get around it: TRIM, Florida's truth-in-taxation law, offers transparency and accountability, yet 58 of 67 counties adopted rates above the rolled-back rate in 2025, raising $1.44 billion above rollback. Full record: Has it worked? For long-time homesteaders, partly; for property taxes as a whole, no. Save Our Homes holds their assessments down, but the rest of the system leaks. The record (Census, BEA, ACS): state and local property tax was $2,003 per person in FY2024 (U.S. $2,132), 2.68% of personal income (26th-highest of 50; U.S. 2.89%). After inflation, collections per person (all state and local property tax divided by residents) rose 21.4% from FY2002 to FY2024 (U.S. +25.9%) and rose 13.5% from FY2019 to FY2024 (U.S. -1.1%). The median homeowner paid $2,993 in 2024 (U.S. $3,211); the median bill rose 16.2% after inflation from 2010 to 2024 (U.S. +9.3%). The Tax Foundation's 2026 ranking puts its effective property tax rate on owner-occupied homes at 0.78%, 24th-lowest of 50. By the same measure it was 0.94% in 2010 (U.S. 1.00% in 2010, 0.94% in 2024). Florida TaxWatch puts FY2025-26 local property taxes at $59.2 billion, more than $20 billion of it paid by homeowners. TRIM and maximum millage: in 2025, 58 of 67 counties adopted rates above the rolled-back rate ($1.44 billion statewide above rollback), each after the required TRIM notices and public hearings. Burden shift: Save Our Homes shifts taxes onto new buyers, renters (through non-homestead property capped at 10%) and businesses; Florida TaxWatch estimates the shift from homestead to non-homestead property at more than $10 billion a year. Portability widens the gap between long-time and new owners. The "recapture" rule lets capped values rise even in falling markets. Non-ad valorem assessments: fire, stormwater, solid waste and similar assessments appear on the tax bill but sit outside millage caps and TRIM; CDDs add assessments on new subdivisions. Fees and sales taxes: charges and fees make up 44% of local own-source revenue (U.S.: 34%), and counties add local option sales surtaxes (average 0.98%). Big counties: Broward County adopted a $9.2 billion FY2026-27 budget with a countywide general millage of 5.6658, presented as a modest rate cut (Caribbean National Weekly, Sept. 23, 2026); under TRIM a lower rate is still a tax increase whenever it exceeds the rolled-back rate. State response: SB 4-F (signed June 24, 2026) ended the per capita income allowance in maximum millage, and HB 1329 requires cities and counties to publish quarterly employee compensation reports and run an annual budget-cutting exercise; the 2025-2026 "Florida DOGE" audits of local spending and Amendment 3, which the state's Revenue Estimating Conference says would cut local revenue about $12 billion a year. | T10: - James Madison Institute, "2026 Florida Amendment Guide" (Sept. 21, 2026). Plain-language guide to the three statewide amendments on the Nov. 3, 2026 ballot. It explains that Amendment 3 phases in a larger homestead exemption, sets a path toward ending non-school homestead taxes, limits local use of property tax revenue and lowers the non-homestead assessment cap. https://jamesmadison.org/2026-florida-amendment-guide/ - Florida TaxWatch, "Florida TaxWatch Unveils ‘Property Tax Resource Center’ to Provide Floridians Independent, Data-Driven Research on Amendment 3" (Aug. 21, 2026). Launches PropertyTaxFL.org, with a county-by-county database of Amendment 3's effects. TaxWatch calls the process that put Amendment 3 on the ballot "rushed" and asks the 2027 Taxation and Budget Reform Commission to vet the issue; its poll with Sachs Media found topline approval would drop to 42 percent, short of the 60 percent needed, if that argument holds with voters. https://floridataxwatch.org/?p=9214 - Tax Foundation, Nicole Fox, "The Real November Ballot Question: What Price Are Floridians Willing to Pay to “Save Their Homes?”" (June 3, 2026). Homestead property is 36.1% of Florida's taxable real property value, and legislative fiscal analysis estimates Amendment 3 would cut local revenue by $4.6 billion in the first year and $8.4 billion in the second, with no plan to replace it, so millage rates on the remaining base could rise. It concludes that "A well-structured property tax levy limit that limits the growth in property tax collections over time is a far more sustainable and structurally sound approach." https://taxfoundation.org/blog/florida-property-tax-proposal/ - James Madison Institute, Doug Wheeler, "Levy Caps for Property Tax Reform in Florida" (March 10, 2026). Collections exceed $55 billion a year, and total assessed value has tripled since 2000 while population grew about 45% and inflation about 70%. Argues for a levy cap tying growth in total property tax revenue to inflation plus population, since homestead exemptions and rebates give short-term relief without locking in control of total tax burdens. https://jamesmadison.org/levy-caps-for-property-tax-reform-in-florida/ - Florida Policy Project (Jeff Brandes, president), quoted in "‘We have a slogan, but we don’t have a policy’: Former Florida lawmaker criticizes property tax relief plan" (Feb. 10, 2026). Brandes, a former state senator, said of the push to cut homestead taxes, "I think what we have is a bumper sticker, we have a slogan, but we don't have a policy." https://www.wflx.com/2026/02/10/we-have-slogan-we-dont-have-policy-former-florida-lawmaker-criticizes-property-tax-relief-plan/ - Florida TaxWatch, "Save Our Taxpayers – Property Tax Relief Must be Accomplished Equitably" (Jan. 15, 2026). Local property taxes total $59.2 billion in FY2025-26, and the shift from homestead to non-homestead property already exceeds $10 billion. Warns against eliminating property taxes without restraining local spending and calls for a "Save Our Taxpayers" amendment capping assessment growth on all property at the Save Our Homes rate. https://floridataxwatch.org/?p=7093 - James Madison Institute, Vance Ginn and Joseph Johns, "Property Tax Relief in Florida: Challenges, Options, and the Path to True Homeownership" (Oct. 15, 2025). Finds that local spending growth has pushed property taxes up even with the Save Our Homes cap, and that any relief "risks being temporary" without a spending limit set at population growth plus inflation, citing Colorado's TABOR as a model. Reviews homestead exemptions, levy caps, surplus buydowns and sales tax swaps, and notes property taxes supply $13.7 billion of the $29.5 billion in statewide school funding. https://jamesmadison.org/property-tax-relief-in-florida-challenges-options-and-the-path-to-true-homeownership/ - Foundation for Government Accountability, Michael Greibrok, "Out-of-Control Spending by Local Governments Leads to Soaring Property Taxes" (Oct. 16, 2024). National report urging state lawmakers to rein in local spending and property taxes. Its Florida examples: Orlando's spending rose from $251 million in 2003 to $934 million in 2014 to $1.8 billion in 2024, and Broward County is building a $140 million, 29-story hotel the county will own. https://thefga.org/research/out-of-control-spending-leads-to-soaring-property-taxes/ Linked list: 10 items on the Analyses sheet (filter State = Florida); every source URL is linked on the Sources sheet. | U10: 2008: Amendment 1 (portability, 10% non-homestead cap, second $25,000 exemption). 2018: Amendment 2 made the 10% cap permanent. 2024: Amendment 5 (index the second homestead exemption to inflation) passed. 2025: Governor DeSantis campaigned to eliminate homestead property taxes; the House passed several joint resolutions; the state launched DOGE audits of county and city budgets. 2026: in special session the Legislature passed HJR 1-F (with implementing SB 4-F), now Amendment 3 on the Nov. 3, 2026 ballot ("Save Our Homes From Excessive Property Taxes"): $150,000 then $250,000 non-school homestead exemption, a path to full exemption, core-services spending restriction, non-homestead cap cut from 10% to 5% for non-school levies, and a five-year residency requirement for new residents. Needs 60%. Also on the ballot: Amendment 2 (exempt agricultural tangible personal property). June 24, 2026: Gov. DeSantis signed SB 4-F (House 75-27, Senate 30-8), which removes per capita personal income growth from the maximum millage calculation effective immediately, whatever happens to Amendment 3, and HB 1329 (local budget transparency: quarterly employee compensation reports and an annual budget-cutting exercise). | V10: 24th (0.78% effective rate; 0.94% in 2010) | W10: Florida has three of four regimes: 10-mill rate caps, Save Our Homes and non-homestead assessment caps, and a statutory levy limit (maximum millage) backed by supermajority votes and the nation's most detailed TRIM notices. It has no local spending cap. Local governments still routinely adopt rates above rollback, and Save Our Homes shifts burden to newcomers and businesses. Amendment 3 (Nov. 2026) would be the largest homestead tax cut in the country if approved. | X10: http://www.leg.state.fl.us/statutes/index.cfm?App_mode=Display_Statute&URL=0200-0299/0200/Sections/0200.065.html http://www.leg.state.fl.us/statutes/index.cfm?App_mode=Display_Statute&URL=1000-1099/1011/Sections/1011.71.html https://floridarevenue.com/property/Documents/comp25.pdf https://www.floridapolicy.org/posts/florida-property-tax-amendment-ballot-language-summary https://taxfoundation.org/research/state-tax/2026-state-tax-ballot-measures/ https://www.lincolninst.edu/app/uploads/2024/12/assessment_limits_2022-3.xlsx https://apps.lincolninst.edu/uploads/summary-tables/rate-limits-summary-tables/rate-limits-2022-4.xlsx https://floridataxwatch.org/Research/Full-Library/truth-in-property-taxation-can-be-hard-to-come-by-3 https://www.flsenate.gov/Laws/Statutes/2025/1011.73 https://www.flsenate.gov/Laws/Statutes/2025/200.091 https://www.flsenate.gov/Laws/Statutes/2025/212.055 https://www.flsenate.gov/Laws/Statutes/2025/97.021 https://www.flsenate.gov/Laws/Statutes/2025/193.155 https://www.flsenate.gov/Laws/Statutes/2025/200.065 https://floridataxwatch.org/?p=7093 https://jamesmadison.org/2026-florida-amendment-guide/ https://www.flcities.com/wp-content/uploads/2026/06/Property-Tax-Legislative-Bill-Summaries-6.4.26.pdf https://www.wusf.org/2026-06-24/desantis-signs-bills-tamp-down-local-taxes-what-to-know https://www.clickorlando.com/news/local/2026/07/08/heres-what-to-know-about-floridas-new-property-tax-law/ https://www.caribbeannationalweekly.com/posts/broward-commissioners-approve-92-billion-budget-with-modest-millage-reduction https://www.wflx.com/2026/02/10/we-have-slogan-we-dont-have-policy-former-florida-lawmaker-criticizes-property-tax-relief-plan/
A11: Georgia | B11: D. Restriction points 7.5 of 18 (assessment cap 2; rate cap 1; truth in taxation 2; rollback 1; school districts covered 1; November-ballot rule 0.25; use restrictions 0.25). Deductions: built-in loopholes -1.5; workarounds in practice -1.5; state buydowns +0; data record -0.5. Total 4 = D (A 11+, B 8.5-10.9, C 5.5-8.4, D 3-5.4, F under 3). Why: Built-in loopholes -1.5: governments exceed the rollback rate by ordinary vote after hearings; the cap limits assessed value only, so cities and counties (with no rate ceiling) can raise millage; non-homestead property is uncapped; and opted-out jurisdictions stay outside the cap until 2027 bills. Workarounds -1.5: 316 governments opted out of HB 581, including the five largest school systems; Atlanta seeks to extend its eight TADs to 2055 for a $5.5 billion plan; relief is shifting to sales taxes (FLOST, LHOST). Buydowns 0: the one-time 2023 $950 million Homeowner Tax Relief Grant is just under 5% of the $19.44 billion FY2024 total and is not recurring. Record -0.5: slow long-run growth per person (15% real, FY2002-FY2022, U.S. 23.4%) offset by fast recent growth (10.1%, FY2019-FY2024, U.S. -1.1%) and real homeowner bill growth of 22.7% since 2010 (U.S. 9.3%). | C11: =((LEFT(D11,3)="Yes")+(LEFT(E11,3)="Yes")+(LEFT(F11,3)="Yes")+(LEFT(G11,3)="Yes"))&" of 4 in force"&IF(((LEFT(D11,7)="Partial")+(LEFT(E11,7)="Partial")+(LEFT(F11,7)="Partial")+(LEFT(G11,7)="Partial"))>0," + "&((LEFT(D11,7)="Partial")+(LEFT(E11,7)="Partial")+(LEFT(F11,7)="Partial")+(LEFT(G11,7)="Partial"))&" partial","")&CHAR(10)&CHAR(10)&IF(LEFT(D11,3)="Yes","✓",IF(LEFT(D11,7)="Partial","◐","✗"))&" Spending limit"&CHAR(10)&IF(LEFT(E11,3)="Yes","✓",IF(LEFT(E11,7)="Partial","◐","✗"))&" Levy limit"&CHAR(10)&IF(LEFT(F11,3)="Yes","✓",IF(LEFT(F11,7)="Partial","◐","✗"))&" Assessment cap"&CHAR(10)&IF(LEFT(G11,3)="Yes","✓",IF(LEFT(G11,7)="Partial","◐","✗"))&" Rate cap" | D11: No. No cap on local budget or spending growth. A revenue cap (voter approval for property tax revenue growth above 3% or inflation) was in the House's 2026 bill (HB 1116) but is not in the enacted SB 33, according to the Georgia Municipal Association. | E11: No. No limit on total property tax revenue growth. Local governments may raise millage above the rollback rate after the Taxpayer Bill of Rights notices and hearings (see TnT). School districts are limited by the 20-mill constitutional rate cap; cities and counties have no general rate ceiling. | F11: Yes. Statewide "floating" homestead exemption (HB 581 of 2024, ratified by voters as Amendment 1 in Nov. 2024 with about 63%): the taxable value of a homestead may rise each year by no more than the prior year's inflation (CPI-U, as set by the Department of Revenue) from a 2024 base year (or the year the owner first claims it); new owners start a new base year, and improvements are added. As enacted it let each county, city and school district opt out by March 1, 2025, and 316 did (68% of school districts, 30% of counties, 26% of cities), including all five of the largest school systems. SB 33 (2026) makes the exemption mandatory for every county, city and school district; jurisdictions that were opted out in 2026 come under it for 2027 tax bills. Many counties also keep older county-specific freezes and floating exemptions adopted by local act. Non-homestead property has no cap. Authority: HB 581 (2024), HB 92 (2025) and SB 33 (signed May 11, 2026); Georgia DOR Rule 560-11-2-.32 (CPI-U index); DOR Informational Bulletin 2025-01. | G11: Partial. School districts may levy no more than 20 mills for operations (with some exceptions by local law or referendum); the statewide school average is about 15 mills. Counties and cities have no general constitutional or statutory millage ceiling. Authority: Ga. Const. art. VIII §VI ¶I. | H11: Yes. School systems are now covered by the mandatory floating homestead exemption (after SB 33 ended opt-outs) and the 20-mill cap, and must follow the Taxpayer Bill of Rights rollback notices and hearings. Two-thirds of school systems had opted out of HB 581 when it was optional. | I11: No. Georgia phased out its small state property levy; it has levied no state property tax since 2016. Authority: HB 386 (2012). | J11: Yes. Statewide: $2,000 of assessed value (about $5,000 of market value at the 40% assessment ratio) exempt from county and school taxes, plus larger senior and disabled-veteran exemptions, plus the inflation-capped floating exemption above. Most relief is local: counties and cities adopt their own homestead exemptions and freezes by local act of the General Assembly and local referendum, producing hundreds of different exemptions. Authority: O.C.G.A. §48-5-44; HB 581 (2024). | K11: Partial. Homeowner Tax Relief Grant (HTRG): a state-funded credit on homestead tax bills, paid in 1999-2008 and revived in 2023 as a one-time $950 million credit (equal to taxes on $18,000 of assessed value). No permanent circuit breaker. | L11: Partial. - Homeowner Tax Relief Grant: the amended FY2026 budget provides $850 million to pay counties and school districts the tax on $18,000 of assessed value of every homestead for the 2026 tax year, credited on the bill. It is a one-time appropriation; the grant was previously funded for the 2023 tax year. - Forestland Protection Grants: the state reimburses local governments and school districts for revenue lost to the preferential assessment of large forest and timberland tracts; $34.9 million in FY2027. FLOST and LHOST are local sales taxes and do not count. Authority: Ga. Const. art. VII, § II-A; HB 973 (AFY2026), Homeowner Tax Relief Grants; O.C.G.A. § 48-5-7.7 and ch. 48-5A; HB 974 (FY2027), Department of Revenue, Forestland Protection Grants. | M11: Yes. Taxpayer Bill of Rights: each year the governing body computes a rollback rate (the rate that raises last year's revenue from existing property); to adopt a higher rate it must advertise a "Notice of Property Tax Increase" stating the percentage increase and hold three public hearings. Since HB 581, assessment notices show an "estimated rollback rate," and if the adopted rate exceeds it the tax bill must say so. Authority: O.C.G.A. §48-5-32.1 (enacted 1999; amended by HB 581, 2024). | N11: Yes. The rollback rate is computed and advertised every year; a government may exceed it only after the required notices and three public hearings, by ordinary vote, with no supermajority or referendum. | O11: No. Millage increases above rollback need only a majority of the governing body. Local acts creating or changing homestead exemptions need local legislation and a local referendum, and LHOST requires a local act plus a referendum. | P11: Partial. SB 33 (2026) narrows the dates on which special elections to raise local revenue (including SPLOST and other sales tax referenda) may be held. Property tax millage itself is set by governing bodies; it does not go to a vote. | Q11: Partial. General millage is unrestricted; school millage funds schools; voter-approved sales taxes are earmarked (SPLOST for capital projects, ESPLOST for school capital, FLOST/LHOST for property tax relief). Community improvement districts levy additional taxes on commercial property for infrastructure within the district. | R11: 159 counties (including consolidated city-county governments such as Athens-Clarke, Augusta-Richmond, Columbus-Muscogee and Macon-Bibb); 537 municipalities; 180 school districts; special taxing districts created by counties; community improvement districts (self-taxing commercial districts); hospital and development authorities (most authorities do not levy property tax). Census of Governments 2022: 1,379 local governments. | S11: Verdict: Failed. Property tax per person rose 27.5% after inflation from FY2002 to FY2024, against 25.9% for the U.S. Why it leaks: Georgia has no levy limit or spending limit, and cities and counties face no rate ceiling; school operations are capped at 20 mills (Ga. Const. art. VIII, §VI, ¶I). A simple board majority can exceed the rollback rate after three hearings. The floating homestead exemption (HB 581, 2024) covers homesteads only. The one-time $950 million Homeowner Tax Relief Grant of 2023 counts against the state. How localities get around it: In all, 316 local governments opted out of HB 581, including the five largest school systems, until SB 33 made it mandatory in 2026. Atlanta proposed extending its eight tax allocation districts to 2055 to steer $5.5 billion to the mayor's Neighborhood Reinvestment Initiative. Full record: Georgia had no binding limit on homeowners' bills until the 2024 floating exemption, and its homeowners saw the second-fastest growth in property tax bills in the country: the median bill rose 43.2% after inflation from 2014 to 2024 (American Community Survey; U.S. +13.3%). The record (Census, BEA, ACS): state and local property tax was $1,735 per person in FY2024 (U.S. $2,132), 2.77% of personal income (23rd-highest of 50; U.S. 2.89%). After inflation, collections per person (all state and local property tax divided by residents) rose 27.5% from FY2002 to FY2024 (U.S. +25.9%) and rose 10.1% from FY2019 to FY2024 (U.S. -1.1%). The median homeowner paid $2,554 in 2024 (U.S. $3,211); the median bill rose 22.7% after inflation from 2010 to 2024 (U.S. +9.3%). The Tax Foundation's 2026 ranking puts its effective property tax rate on owner-occupied homes at 0.79%, 26th-lowest of 50. By the same measure it was 0.83% in 2010 (U.S. 1.00% in 2010, 0.94% in 2024). The one-time $950 million Homeowner Tax Relief Grant (2023) lowered bills for a single year. The 2024 reform then showed how local governments avoid limits when given the choice: 316 of them opted out of the floating homestead exemption, including about two-thirds of school districts and every one of the five largest school systems, together covering counties with 83% of the population (Tax Foundation). The Legislature responded in 2026 by making the cap mandatory. Remaining gaps: (1) the cap applies to assessed value only, so governments can raise millage (cities and counties face no rate ceiling); (2) non-homestead property is uncapped; (3) the rollback rate is disclosure only, so governments exceed it after hearings; (4) revenue relief is increasingly delivered by shifting to sales taxes (SPLOST, ESPLOST, FLOST, LHOST); local sales taxes already supply 31.7% of local taxes (U.S.: 18.5%) and the average combined rate is 7.49%. TIF: Atlanta proposed extending its eight tax allocation districts to 2055 to direct $5.5 billion to the mayor's Neighborhood Reinvestment Initiative, which would keep growth in the TAD tax base away from the general levies of the city, county and schools for three more decades (Center for Civic Innovation, Oct. 19, 2025); Fulton County commissioners opted the county out of the extension in July 2026 (AJC, July 2026). Process: SB 33 was passed in the session's final minutes by inserting the failed HB 1116's language into an unrelated Senate hemp bill; critics argue it violates the constitutional rule that revenue bills originate in the House. | T11: - Georgia Public Policy Foundation, "Guide to the Issues 2026: Thirty years after the first edition" (Oct. 1, 2026). Says "rising assessments keep pushing bills higher even when no one votes to raise the rate" and recommends a levy limit: "A levy limit, which caps growth in a local government's total property tax revenue, would restrain that trend without shifting the burden onto new homeowners." https://www.georgiapolicy.org/news/guide-to-the-issues-2026-thirty-years-after-the-first-edition/ - Common Sense Institute Iowa, "Iowa Leads the Nation in Property Tax Relief: Ranking State Reforms of the Past Decade" (Aug. 6, 2026). Places Georgia's HB 581 and HR 1022 (2024) ninth nationally by net taxpayer savings per household among 2016-2026 property tax relief bills, counting savings without state backfills. https://archive.commonsenseinstituteus.org/iowa/research/taxes-and-fees/iowa-leads-the-nation-in-property-tax-relief-ranking-state-reforms-of-the-past-decade - Tax Foundation, Janelle Fritts, "Georgia Tax Reform 2026: Property Tax Relief & Income Tax Relief" (April 1, 2026). Backs HB 1116's 3% levy limit on property tax revenue growth, calling levy limits "the most economically efficient and structurally sound way of curtailing the growth of property tax bills over time," and warns that any tax swap that substantially reduces reliance on property taxes would make the tax code less efficient. https://taxfoundation.org/blog/georgia-tax-reform-income-taxes-property-taxes/ - Americans for Prosperity-Georgia, "AFP-GA Applauds Senate Passage of HB 1116" (March 31, 2026). Supports HB 1116's requirements that local governments give transparent notice of a proposed tax increase, hold a public hearing on it and put all property tax ballot measures on primary or general election dates. The final version of HB 1116 failed in the Senate on April 2, 2026, and much of it moved into SB 33. https://americansforprosperity.org/press-release/afp-ga-applauds-senate-passage-of-hb-1116/ - Georgia Public Policy Foundation, Chris Denson, "How Can We Cap Property Taxes in Georgia?" (Jan. 1, 2026). Notes that 123 of Georgia's 180 school districts (68%) opted out of the HB 581 floating homestead exemption even though 63% of voters approved it, and proposes a levy limit, such as 3% a year or inflation, that forces millage rollbacks when rising values push revenue past the cap, with a local referendum to override it. https://www.georgiapolicy.org/news/how-can-we-cap-property-taxes-in-georgia/ - Tax Foundation, "Localities Opt Out of Georgia's New Homestead Tax Exemption" (April 17, 2025). Documents the 316 opt-outs from Secretary of State data, warns that two parallel systems undermine simplicity and neutrality, and urges a uniform system with effective levy limits to prevent unauthorized increases in revenue and bills. https://taxfoundation.org/blog/georgia-property-tax-reform/ - Georgia Public Policy Foundation, "What the 2025 legislative session means for Georgia taxpayers" (April 3, 2025). Calls the school districts' opt-outs from the HB 581 floating exemption "troubling, if not ironic" because those districts hold about $6.5 billion in reserves; reviews HB 92's reopening of the opt-out window and the path to rescind it. https://www.georgiapolicy.org/news/what-the-2025-legislative-session-means-for-georgia-taxpayers/ - Georgia Center for Opportunity (State Policy Network affiliate): no property tax report since 2021 was found. Linked list: 7 items on the Analyses sheet (filter State = Georgia); every source URL is linked on the Sources sheet. | U11: 2023: one-time $950 million Homeowner Tax Relief Grant. 2024: HB 581 (floating homestead exemption with opt-out, FLOST, estimated rollback rate) and Amendment 1 (approved, about 63%). 2025: HB 92 reopened the opt-out window and added incentives for school systems to opt back in. 2026: HB 1116 (homestead tax elimination path, LHOST, 3%/inflation revenue cap) failed in the Senate 24-28; its core was added to SB 33, which passed on the final night and was signed May 11, 2026 without the revenue cap: mandatory floating exemption, LHOST, FLOST eligibility for all, new limits on special election dates. June 17-23, 2026 special session: nearly 100 local acts creating LHOST-funded homestead exemptions were introduced so counties could hold referendums on Nov. 3; none won the two-thirds vote local acts need in a special session, so no LHOST question will be on the 2026 ballot (Georgia Municipal Association). Nov. 3, 2026 ballot: Amendment 1 (HR 32, 2025; raise conservation-use acreage limit from 2,000 to 4,000 acres) is the only property tax question; Amendments 2 (nonpartisan probate judge elections) and 3 (Next Generation 9-1-1 fund) do not concern property tax. 2025-2026: Atlanta proposed extending its eight tax allocation districts to 2055 ($5.5 billion reinvestment plan); Fulton County commissioners opted the county out in July 2026. | V11: 26th (0.79% effective rate; 0.83% in 2010) | W11: Georgia now has a mandatory statewide homestead assessment cap (inflation) and a disclosure-based rollback system, plus a 20-mill school rate cap. It has no levy limit and no local spending cap; the 2026 attempt at a 3%/inflation revenue cap was dropped. The opt-out episode is the clearest recent example of local governments using an escape hatch the moment one is offered. | X11: https://taxfoundation.org/blog/georgia-property-tax-reform/ https://billtracker.gacities.com/legislation/69550 https://www.gacities.com/articles/the-2026-session-in-review-what-passed-what-didnt-and-what-it-means https://capitol-beat.org/2026/05/kemp-signs-legislation-to-cut-income-taxes-and-reduce-homeowner-property-tax-increases/ https://capitol-beat.org/2026/04/georgia-republicans-push-through-last-minute-income-and-property-tax-cuts/ https://georgiarecorder.com/2026/05/11/kemp-approves-property-tax-relief-for-georgia-homeowners-amid-concerns-over-local-revenues-process/ https://appealally.com/blog/article/georgia-property-tax-cap-sb-33 https://dor.georgia.gov/media/35186/download https://atlantarealtors.com/resources/news/detail/georgia-property-owners-receive-tax-break https://www.lincolninst.edu/app/uploads/2024/10/truth_in_taxation_2024.xlsx https://law.justia.com/codes/georgia/title-48/chapter-5/article-2/part-1/section-48-5-44-2/ https://www.legis.ga.gov/api/document/docs/default-source/house-budget-and-research-office-document-library/newsandhighlights/2024/2024_policy_brief_hb_581_property_tax_reform.pdf https://www.gacities.com/articles/general-assembly-concludes-special-session https://www.georgiapolicy.org/news/what-the-2025-legislative-session-means-for-georgia-taxpayers/ https://www.georgiapolicy.org/news/guide-to-the-issues-2026-thirty-years-after-the-first-edition/ https://www.news4jax.com/voters-guide/2026/10/08/2026-voters-guide-georgia-constitutional-amendments/ https://civicatlanta.org/blog/2025-10-19-atlanta-weighs-tad-extension https://www.ajc.com/news/2026/07/fulton-commissioners-opt-out-of-atlanta-mayors-tax-extension-plan/ https://www.gacities.com/articles/sb-33-the-homeownership-opportunity-and-market-equalization-act-of-2026
